Workbook

Sheet FAR
A1: Scenario | D1: FinancialYear | E1: FinancialPeriod | F1: AssetRegisterItemID | G1: MunicipalAssetID | H1: ParentAssetRegisterItem_ID | I1: MainAssetDescription | J1: MainAssetID | K1: AssetDescription | L1: OldBarcode | M1: Barcode | N1: ImageRef | O1: AssetType | P1: AssetCategory | Q1: AssetSubCategory | R1: AssetClass | S1: MeasurementType_ID2 | T1: AssetStatus | U1: CIDMSSubComponentType | V1: CIDMSComponentType | W1: CIDMSAccountingGroup | X1: CIDMSSubAccountingGroup | Y1: CIDMSAssetClass | Z1: CIDMSAssetGroupType | AA1: CIDMSAssetType | AB1: NatureOfAddition | AC1: InfrastructurOrNonInfrastructure | AD1: CashNonCashGeneratingUnit | AE1: FinancialStatus | AF1: TakeOnDate | AG1: AquisitionDate | AH1: System_In_Service_Date | AI1: DisposalDate | AJ1: DisposalReason | AK1: Impairment_Date | AL1: DateModified | AM1: VerificationDate | AN1: VerificationDoneBy | AO1: YearConstructed | AP1: CommisioningDate | AQ1: ConstructionMaterial | AR1: ForecastReplacementYear | AS1: AssetCondition | AT1: InsuranceCover | AU1: InsurancePolicy | AV1: Warranty | AW1: CurrentReplacementCostCRC | AX1: DepreciatedReplacementCostDRC | AY1: AnnualisedMaintenanceCRC | AZ1: AnnualMaintenanceBudgetNeed | BA1: DepreciationMethod | BB1: UsefulLifeYearComponent | BC1: UsefulLifeMonthComponent | BD1: UsefulLifeDaysComponent | BE1: Remaining_Useful_Life_Year | BF1: Remaining_Useful_Life_Months | BG1: Remaining_Useful_Life_Days | BH1: RemainingUsefulllifeAtTakeon | BI1: UOM | BJ1: Dim1 | BK1: Dim2 | BL1: Dim3 | BM1: DimensionQuantity | BN1: Quantity | BO1: Diameter | BP1: Capacity | BQ1: SGNumberChange_ID | BR1: DeedNumber | BS1: ErfNumber | BT1: ErfSizeM2 | BU1: PortionNumber | BV1: UnitNumber | BW1: RegistrationNumber | BX1: SerialNumber | BY1: CustodianName | BZ1: CustodianIdNumber | CA1: BasicMunicipalServices | CB1: CriticalityGrade | CC1: PerformanceGrade | CD1: UtilisationGrade | CE1: InfrastructureHealthGrade | CF1: ConsequenceOfFailure | CG1: Risk | CH1: AssetOwnership | CI1: Department | CJ1: Division | CK1: Town | CL1: StreetName | CM1: Building | CN1: Ward | CO1: Zoning | CP1: FloorArea | CQ1: RoomNumber | CR1: Suburb | CS1: WellKnownTextWKT | CT1: GISID | CU1: Latitude | CV1: Longitude | CW1: FundingSourceAmount | CX1: FundingSourceNumber | CY1: FundType | CZ1: CostOfAddition | DA1: Revaluation_Date | DB1: Revaluation_Value | DC1: Accumulated_Revalutions_Opening_Balance | DD1: Revaluation_Reserve_Impairments_OpeningBalance | DE1: Revaluation_Reserve_Impairments | DF1: Revaluation_Reserve_Impairment_Reversals | DG1: Revaluation_Reserve_Impairments_ClosingBalance | DH1: Revaluation_Reserve_Revaluations | DI1: Revaluation_Reserve_Disposals | DJ1: Refurb_Revaluation | DK1: Accumulated_Revaluation_Closing_Balance | DL1: Movement_In_Revaluation_Reserve | DM1: DepreciationOffsetOpeningBalance | DN1: DepreciationOffset | DO1: DepreciationOffsetClosingBalance | DP1: Revaluation_Surplus_Deficit | DQ1: Deemed_Cost | DR1: Cost_OpeningBalance | DS1: Cost_RestatedOpeningBalance | DT1: Cost_Acquisitions | DU1: Cost_RisidualValue | DV1: WorkInProgress | DW1: TransferFromAmount | DX1: TransferToAmount | DY1: RefurbishmentCredit | DZ1: RefurbishmentDebit | EA1: Cost_FairValueAdjustment | EB1: Revaluation_Adjustment | EC1: Cost_Disposal | ED1: Cost_ClosingBalance | EE1: AccumulatedDepreciation_OpeningBalance | EF1: AccumulatedDepreciation_RestatedOpeningBalance | EG1: AccumulatedDepreciation_Depreciation | EH1: DepreciationAdjustments | EI1: AccumulatedDepreciation_Disposal | EJ1: Refurb_Depreciation | EK1: AccumulatedDepreciation_ClosingBalance | EL1: AccumulatedImpairment_OpeningBalance | EM1: AccumulatedImpairment_RestatedOpeningBalance | EN1: AccumulatedImpairmentImpairment | EO1: AccumulatedImpairment_ReversalOfImpairment | EP1: AccumulatedImpairment_Disposal | EQ1: AccumulatedImpairment_ClosingBalance | ER1: CarryingAmount | ES1: Disposal_Proceeds | ET1: Disposal_Profit_Loss | EU1: DonorIDRegistrationNumberParastatalCode | EV1: DonorNameCompanyRegistrationNumberParastatalName | EW1: Date_Donated | EX1: Make | EY1: Model | EZ1: Custom_1 | FA1: Custom_2 | FB1: Custom_3 | FC1: Custom_4 | FD1: Custom_5 | FE1: Custom_6 | FF1: Custom_7 | FG1: Custom_8 | FH1: Custom_9
A4: 1.1 - Cost increase due to incorrect t treatment of WIP, Retentions, VAT, etc. Cost increases from R3,046,098.51 to R3,807,623.14 | C4: Original values captured | D4: 2025/2026 | E4: 0 | F4: 10767 | G4: RD07909/000 | H4: RD07909 | I4: Unpaved Road | K4: Unpaved Road | O4: Property, Plant and Equipment | P4: Roads Infrastructure | Q4: Roads | R4: Unpaved Road | S4: Revaluation Module | U4: Unpaved Road | V4: Unpaved Road | W4: Property, plant and equipment | X4: Infrastructure assets | Y4: Roads infrastructure | Z4: Roads | AA4: Pavements | AB4: New | AC4: Infrastructure | AD4: Non Cash | AE4: EAR (Existing Asset Register) | AF4: 45306 | AG4: 45306 | AH4: 45306 | AL4: 45306 | AM4: 45473 | AN4: Lundi Knox Nxawe | AP4: 45473 | AS4: Good | AT4: No | AV4: No | AW4: 3046098.5 | AX4: =ER4 -> 2601284.8 | AY4: 0 | AZ4: 0 | BA4: Straight-line | BB4: 10 | BC4: 120 | BD4: 3650 | BE4: =BG4/365 -> 8.539726 | BF4: =BE4*12 -> 102.47671 | BG4: ='1'!$B$28 -> 3117 | BI4: Square Meter | BN4: 1 | BO4: 0 | BP4: 0 | BY4: Zanele Nontando Mbusi | BZ4: 830910xxxxxxx | CA4: Yes | CB4: Important | CC4: Meets requirements | CD4: Normal use | CE4: Very good | CF4: Moderate | CG4: Medium | CH4: Mnquma Local Municipality | CI4: Infrastructural Planning & Development | CJ4: Civil Services | CK4: Butterworth | CN4: Ward 1 | CU4: -32.188584 | CV4: 28.055332 | CW4: =DS4 -> 3046098.5 | CX4: 0 | DA4: 1 | DB4: 3036924.8 | DC4: 0 | DD4: 0 | DE4: 0 | DF4: 0 | DG4: 0 | DH4: 0 | DI4: 0 | DJ4: 0 | DK4: 0 | DL4: 0 | DM4: 0 | DN4: 0 | DO4: 0 | DP4: 0 | DQ4: Yes | DR4: ='1'!$B$5 -> 3046098.5 | DS4: ='1'!$B$5 -> 3046098.5 | DT4: 0 | DU4: 1 | DV4: 0 | DW4: 0 | DX4: 0 | DY4: 0 | DZ4: 0 | EA4: 0 | EB4: 0 | EC4: 0 | ED4: =DS4+DT4+DV4-DW4+DX4-DY4+DZ4+EA4+EB4 -> 3046098.5 | EE4: ='1'!$B$15 -> 140203.94 | EF4: ='1'!$B$15 -> 140203.94 | EG4: ='1'!$B$21 -> 304609.75 | EH4: 0 | EI4: 0 | EJ4: 0 | EK4: =EF4+EG4+EH4-EI4-EJ4 -> 444813.69 | EL4: 0 | EM4: 0 | EN4: 0 | EO4: 0 | EP4: 0 | EQ4: =EM4+EN4-EO4-EP4 -> 0 | ER4: =ED4-EK4-EQ4 -> 2601284.8 | ES4: 0 | ET4: 0 | EZ4: Roads | FA4: {539308C0-87C6-4256-BD2D-FD6198DF208C}
A5: 1.1 - Cost increase due to incorrect t treatment of WIP, Retentions, VAT, etc. Cost increases from R3,046,098.51 to R3,807,623.14 | C5: Corrected values | D5: 2025/2026 | E5: 0 | F5: 10767 | G5: RD07909/000 | H5: RD07909 | I5: Unpaved Road | K5: Unpaved Road | O5: Property, Plant and Equipment | P5: Roads Infrastructure | Q5: Roads | R5: Unpaved Road | S5: Revaluation Module | U5: Unpaved Road | V5: Unpaved Road | W5: Property, plant and equipment | X5: Infrastructure assets | Y5: Roads infrastructure | Z5: Roads | AA5: Pavements | AB5: New | AC5: Infrastructure | AD5: Non Cash | AE5: EAR (Existing Asset Register) | AF5: 45306 | AG5: 45306 | AH5: 45306 | AL5: 45306 | AM5: 45473 | AN5: Lundi Knox Nxawe | AP5: 45473 | AS5: Good | AT5: No | AV5: No | AW5: 3807623.1 | AX5: =ER5 -> 3251606 | AY5: 0 | AZ5: 0 | BA5: Straight-line | BB5: 10 | BC5: 120 | BD5: 3650 | BE5: =BG5/365 -> 8.539726 | BF5: =BE5*12 -> 102.47671 | BG5: ='1'!$C$28 -> 3117 | BI5: Square Meter | BN5: 1 | BO5: 0 | BP5: 0 | BY5: Zanele Nontando Mbusi | BZ5: 830910xxxxxxx | CA5: Yes | CB5: Important | CC5: Meets requirements | CD5: Normal use | CE5: Very good | CF5: Moderate | CG5: Medium | CH5: Mnquma Local Municipality | CI5: Infrastructural Planning & Development | CJ5: Civil Services | CK5: Butterworth | CN5: Ward 1 | CU5: -32.188584 | CV5: 28.055332 | CW5: =DS5 -> 3807623.1 | CX5: 0 | DA5: 1 | DB5: 3036924.8 | DC5: 0 | DD5: 0 | DE5: 0 | DF5: 0 | DG5: 0 | DH5: 0 | DI5: 0 | DJ5: 0 | DK5: 0 | DL5: 0 | DM5: 0 | DN5: 0 | DO5: 0 | DP5: 0 | DQ5: Yes | DR5: ='1'!$C$5 -> 3807623.1 | DS5: ='1'!$C$5 -> 3807623.1 | DT5: 0 | DU5: 1 | DV5: 0 | DW5: 0 | DX5: 0 | DY5: 0 | DZ5: 0 | EA5: 0 | EB5: 0 | EC5: 0 | ED5: =DS5+DT5+DV5-DW5+DX5-DY5+DZ5+EA5+EB5 -> 3807623.1 | EE5: ='1'!$C$15 -> 175254.94 | EF5: ='1'!$C$15 -> 175254.94 | EG5: ='1'!$C$21 -> 380762.21 | EH5: 0 | EI5: 0 | EJ5: 0 | EK5: =EF5+EG5+EH5-EI5-EJ5 -> 556017.15 | EL5: 0 | EM5: 0 | EN5: 0 | EO5: 0 | EP5: 0 | EQ5: =EM5+EN5-EO5-EP5 -> 0 | ER5: =ED5-EK5-EQ5 -> 3251606 | ES5: 0 | ET5: 0 | EZ5: Roads | FA5: {539308C0-87C6-4256-BD2D-FD6198DF208C}
A6: 1.1 - Cost increase due to incorrect t treatment of WIP, Retentions, VAT, etc. Cost increases from R3,046,098.51 to R3,807,623.14 | C6: Net Correction | DS6: =DS4-DS5 -> -761524.63 | ED6: =ED4-ED5 -> -761524.63 | EE6: =EE4-EE5 -> -35051 | EF6: =EF4-EF5 -> -35051 | EG6: =EG4-EG5 -> -76152.46 | EH6: =EH4-EH5 -> 0 | EI6: =EI4-EI5 -> 0 | EJ6: =EJ4-EJ5 -> 0 | EK6: =EK4-EK5 -> -111203.46 | ER6: =ER4-ER5 -> -650321.17
A8: Description | C8: Current balance | D8: Corrected Balance | E8: Journal - Debit/ (Credit)
A9: Cost - Roads - Periods before 2024
A10: Cost - Roads - Period 2024 | C10: =DS4 -> 3046098.5 | D10: =DS5 -> 3807623.1 | E10: =D10-C10 -> 761524.63
A11: Cost - Roads - Period 2025
A12: Accumulated Surplus/WIP/Accruals/VAT before 2025 | E12: =-E10 -> -761524.63
A13: Accumulated Surplus/WIP/Accruals/VAT 2025
A14: Accumulated Depreciation - Roads - Before 2024
A15: Accumulated Depreciation - Roads - 2024 | C15: ='1'!$B$11 -> 140203.94 | D15: ='1'!$C$11 -> 175254.94 | E15: =C15-D15 -> -35051
A16: Accumulated Depreciation - Roads - 2025 | C16: ='1'!$B$21 -> 304609.75 | D16: ='1'!$C$21 -> 380762.21 | E16: =C16-D16 -> -76152.46
A17: Accumulated Surplus - Deprecation Charges before 2025 | C17: =C15 -> 140203.94 | D17: =D15 -> 175254.94 | E17: =D17-C17 -> 35051
A18: Accumulated Surplus - Deprecation Charges 2025 | C18: =C16 -> 304609.75 | D18: =D16 -> 380762.21 | E18: =D18-C18 -> 76152.46
A21: 1.2 - Cost decrease due to incorrect t treatment of WIP, Retentions, VAT, etc. Cost decreases from R3,046,098.51 to R2,284,573.88 | C21: Original values captured | D21: 2025/2026 | E21: 0 | F21: 10767 | G21: RD07909/000 | H21: RD07909 | I21: Unpaved Road | K21: Unpaved Road | O21: Property, Plant and Equipment | P21: Roads Infrastructure | Q21: Roads | R21: Unpaved Road | S21: Revaluation Module | U21: Unpaved Road | V21: Unpaved Road | W21: Property, plant and equipment | X21: Infrastructure assets | Y21: Roads infrastructure | Z21: Roads | AA21: Pavements | AB21: New | AC21: Infrastructure | AD21: Non Cash | AE21: EAR (Existing Asset Register) | AF21: 45306 | AG21: 45306 | AH21: 45306 | AL21: 45306 | AM21: 45473 | AN21: Lundi Knox Nxawe | AP21: 45473 | AS21: Good | AT21: No | AV21: No | AW21: 3046098.5 | AX21: =ER21 -> 2601284.8 | AY21: 0 | AZ21: 0 | BA21: Straight-line | BB21: 10 | BC21: 120 | BD21: 3650 | BE21: =BG21/365 -> 8.539726 | BF21: =BE21*12 -> 102.47671 | BG21: ='1'!$B$28 -> 3117 | BI21: Square Meter | BN21: 1 | BO21: 0 | BP21: 0 | BY21: Zanele Nontando Mbusi | BZ21: 830910xxxxxxx | CA21: Yes | CB21: Important | CC21: Meets requirements | CD21: Normal use | CE21: Very good | CF21: Moderate | CG21: Medium | CH21: Mnquma Local Municipality | CI21: Infrastructural Planning & Development | CJ21: Civil Services | CK21: Butterworth | CN21: Ward 1 | CU21: -32.188584 | CV21: 28.055332 | CW21: =DS21 -> 3046098.5 | CX21: 0 | DA21: 1 | DB21: 3036924.8 | DC21: 0 | DD21: 0 | DE21: 0 | DF21: 0 | DG21: 0 | DH21: 0 | DI21: 0 | DJ21: 0 | DK21: 0 | DL21: 0 | DM21: 0 | DN21: 0 | DO21: 0 | DP21: 0 | DQ21: Yes | DR21: ='1'!$B$5 -> 3046098.5 | DS21: ='1'!$B$5 -> 3046098.5 | DT21: 0 | DU21: 1 | DV21: 0 | DW21: 0 | DX21: 0 | DY21: 0 | DZ21: 0 | EA21: 0 | EB21: 0 | EC21: 0 | ED21: =DS21+DT21+DV21-DW21+DX21-DY21+DZ21+EA21+EB21 -> 3046098.5 | EE21: ='1'!$B$15 -> 140203.94 | EF21: ='1'!$B$15 -> 140203.94 | EG21: ='1'!$B$21 -> 304609.75 | EH21: 0 | EI21: 0 | EJ21: 0 | EK21: =EF21+EG21+EH21-EI21-EJ21 -> 444813.69 | EL21: 0 | EM21: 0 | EN21: 0 | EO21: 0 | EP21: 0 | EQ21: =EM21+EN21-EO21-EP21 -> 0 | ER21: =ED21-EK21-EQ21 -> 2601284.8 | ES21: 0 | ET21: 0 | EZ21: Roads | FA21: {539308C0-87C6-4256-BD2D-FD6198DF208C}
A22: 1.2 - Cost decrease due to incorrect t treatment of WIP, Retentions, VAT, etc. Cost decreases from R3,046,098.51 to R2,284,573.88 | C22: Corrected values | D22: 2025/2026 | E22: 0 | F22: 10767 | G22: RD07909/000 | H22: RD07909 | I22: Unpaved Road | K22: Unpaved Road | O22: Property, Plant and Equipment | P22: Roads Infrastructure | Q22: Roads | R22: Unpaved Road | S22: Revaluation Module | U22: Unpaved Road | V22: Unpaved Road | W22: Property, plant and equipment | X22: Infrastructure assets | Y22: Roads infrastructure | Z22: Roads | AA22: Pavements | AB22: New | AC22: Infrastructure | AD22: Non Cash | AE22: EAR (Existing Asset Register) | AF22: 45306 | AG22: 45306 | AH22: 45306 | AL22: 45306 | AM22: 45473 | AN22: Lundi Knox Nxawe | AP22: 45473 | AS22: Good | AT22: No | AV22: No | AW22: 3807623.1 | AX22: =ER22 -> 1950963.6 | AY22: 0 | AZ22: 0 | BA22: Straight-line | BB22: 10 | BC22: 120 | BD22: 3650 | BE22: =BG22/365 -> 8.539726 | BF22: =BE22*12 -> 102.47671 | BG22: ='1'!$D$28 -> 3117 | BI22: Square Meter | BN22: 1 | BO22: 0 | BP22: 0 | BY22: Zanele Nontando Mbusi | BZ22: 830910xxxxxxx | CA22: Yes | CB22: Important | CC22: Meets requirements | CD22: Normal use | CE22: Very good | CF22: Moderate | CG22: Medium | CH22: Mnquma Local Municipality | CI22: Infrastructural Planning & Development | CJ22: Civil Services | CK22: Butterworth | CN22: Ward 1 | CU22: -32.188584 | CV22: 28.055332 | CW22: =DS22 -> 2284573.9 | CX22: 0 | DA22: 1 | DB22: 3036924.8 | DC22: 0 | DD22: 0 | DE22: 0 | DF22: 0 | DG22: 0 | DH22: 0 | DI22: 0 | DJ22: 0 | DK22: 0 | DL22: 0 | DM22: 0 | DN22: 0 | DO22: 0 | DP22: 0 | DQ22: Yes | DR22: ='1'!$C$5 -> 3807623.1 | DS22: ='1'!$D$5 -> 2284573.9 | DT22: 0 | DU22: 1 | DV22: 0 | DW22: 0 | DX22: 0 | DY22: 0 | DZ22: 0 | EA22: 0 | EB22: 0 | EC22: 0 | ED22: =DS22+DT22+DV22-DW22+DX22-DY22+DZ22+EA22+EB22 -> 2284573.9 | EE22: ='1'!$D$15 -> 105152.94 | EF22: ='1'!$D$15 -> 105152.94 | EG22: ='1'!$D$21 -> 228457.29 | EH22: 0 | EI22: 0 | EJ22: 0 | EK22: =EF22+EG22+EH22-EI22-EJ22 -> 333610.23 | EL22: 0 | EM22: 0 | EN22: 0 | EO22: 0 | EP22: 0 | EQ22: =EM22+EN22-EO22-EP22 -> 0 | ER22: =ED22-EK22-EQ22 -> 1950963.6 | ES22: 0 | ET22: 0 | EZ22: Roads | FA22: {539308C0-87C6-4256-BD2D-FD6198DF208C}
A23: 1.2 - Cost decrease due to incorrect t treatment of WIP, Retentions, VAT, etc. Cost decreases from R3,046,098.51 to R2,284,573.88 | C23: Net Correction | DS23: =DS21-DS22 -> 761524.63 | ED23: =ED21-ED22 -> 761524.63 | EE23: =EE21-EE22 -> 35051 | EF23: =EF21-EF22 -> 35051 | EG23: =EG21-EG22 -> 76152.46 | EH23: =EH21-EH22 -> 0 | EI23: =EI21-EI22 -> 0 | EJ23: =EJ21-EJ22 -> 0 | EK23: =EK21-EK22 -> 111203.46 | ER23: =ER21-ER22 -> 650321.17
A25: Description | C25: Current balance | D25: Corrected Balance | E25: Journal - Debit/ (Credit)
A26: Cost - Roads - Periods before 2024
A27: Cost - Roads - Period 2024 | C27: =DS21 -> 3046098.5 | D27: =DS22 -> 2284573.9 | E27: =D27-C27 -> -761524.63
A28: Cost - Roads - Period 2025
A29: Accumulated Surplus/WIP/Accruals/VAT before 2025 | E29: =-E27 -> 761524.63
A30: Accumulated Surplus/WIP/Accruals/VAT 2025 | E30: =-E28 -> 0
A31: Accumulated Depreciation - Roads - Before 2024
A32: Accumulated Depreciation - Roads - 2024 | C32: ='1'!$B$11 -> 140203.94 | D32: ='1'!$D$11 -> 105152.94 | E32: =C32-D32 -> 35051
A33: Accumulated Depreciation - Roads - 2025 | C33: ='1'!$B$21 -> 304609.75 | D33: ='1'!$D$21 -> 228457.29 | E33: =C33-D33 -> 76152.46
A34: Accumulated Surplus - Deprecation Charges before 2025 | C34: =C32 -> 140203.94 | D34: =D32 -> 105152.94 | E34: =D34-C34 -> -35051
A35: Accumulated Surplus - Deprecation Charges 2025 | C35: =C33 -> 304609.75 | D35: =D33 -> 228457.29 | E35: =D35-C35 -> -76152.46
D39: FinancialYear | E39: FinancialPeriod | F39: AssetRegisterItemID | G39: MunicipalAssetID | H39: ParentAssetRegisterItem_ID | I39: MainAssetDescription | J39: MainAssetID | K39: AssetDescription | L39: OldBarcode | M39: Barcode | N39: ImageRef | O39: AssetType | P39: AssetCategory | Q39: AssetSubCategory | R39: AssetClass | S39: MeasurementType_ID2 | T39: AssetStatus | U39: CIDMSSubComponentType | V39: CIDMSComponentType | W39: CIDMSAccountingGroup | X39: CIDMSSubAccountingGroup | Y39: CIDMSAssetClass | Z39: CIDMSAssetGroupType | AA39: CIDMSAssetType | AB39: NatureOfAddition | AC39: InfrastructurOrNonInfrastructure | AD39: CashNonCashGeneratingUnit | AE39: FinancialStatus | AF39: TakeOnDate | AG39: AquisitionDate | AH39: System_In_Service_Date | AI39: DisposalDate | AJ39: DisposalReason | AK39: Impairment_Date | AL39: DateModified | AM39: VerificationDate | AN39: VerificationDoneBy | AO39: YearConstructed | AP39: CommisioningDate | AQ39: ConstructionMaterial | AR39: ForecastReplacementYear | AS39: AssetCondition | AT39: InsuranceCover | AU39: InsurancePolicy | AV39: Warranty | AW39: CurrentReplacementCostCRC | AX39: DepreciatedReplacementCostDRC | AY39: AnnualisedMaintenanceCRC | AZ39: AnnualMaintenanceBudgetNeed | BA39: DepreciationMethod | BB39: UsefulLifeYearComponent | BC39: UsefulLifeMonthComponent | BD39: UsefulLifeDaysComponent | BE39: Remaining_Useful_Life_Year | BF39: Remaining_Useful_Life_Months | BG39: Remaining_Useful_Life_Days | BH39: RemainingUsefulllifeAtTakeon | BI39: UOM | BJ39: Dim1 | BK39: Dim2 | BL39: Dim3 | BM39: DimensionQuantity | BN39: Quantity | BO39: Diameter | BP39: Capacity | BQ39: SGNumberChange_ID | BR39: DeedNumber | BS39: ErfNumber | BT39: ErfSizeM2 | BU39: PortionNumber | BV39: UnitNumber | BW39: RegistrationNumber | BX39: SerialNumber | BY39: CustodianName | BZ39: CustodianIdNumber | CA39: BasicMunicipalServices | CB39: CriticalityGrade | CC39: PerformanceGrade | CD39: UtilisationGrade | CE39: InfrastructureHealthGrade | CF39: ConsequenceOfFailure | CG39: Risk | CH39: AssetOwnership | CI39: Department | CJ39: Division | CK39: Town | CL39: StreetName | CM39: Building | CN39: Ward | CO39: Zoning | CP39: FloorArea | CQ39: RoomNumber | CR39: Suburb | CS39: WellKnownTextWKT | CT39: GISID | CU39: Latitude | CV39: Longitude | CW39: FundingSourceAmount | CX39: FundingSourceNumber | CY39: FundType | CZ39: CostOfAddition | DA39: Revaluation_Date | DB39: Revaluation_Value | DC39: Accumulated_Revalutions_Opening_Balance | DD39: Revaluation_Reserve_Impairments_OpeningBalance | DE39: Revaluation_Reserve_Impairments | DF39: Revaluation_Reserve_Impairment_Reversals | DG39: Revaluation_Reserve_Impairments_ClosingBalance | DH39: Revaluation_Reserve_Revaluations | DI39: Revaluation_Reserve_Disposals | DJ39: Refurb_Revaluation | DK39: Accumulated_Revaluation_Closing_Balance | DL39: Movement_In_Revaluation_Reserve | DM39: DepreciationOffsetOpeningBalance | DN39: Depreciation_Offset | DO39: DepreciationOffsetClosingBalance | DP39: Revaluation_Surplus_Deficit | DQ39: Deemed_Cost | DR39: Cost_OpeningBalance | DS39: Cost_RestatedOpeningBalance | DT39: Cost_Acquisitions | DU39: Cost_RisidualValue | DV39: WorkInProgress | DW39: TransferFromAmount | DX39: TransferToAmount | DY39: RefurbishmentCredit | DZ39: RefurbishmentDebit | EA39: Cost_FairValueAdjustment | EB39: Revaluation_Adjustment | EC39: Cost_Disposal | ED39: Cost_ClosingBalance | EE39: AccumulatedDepreciation_OpeningBalance | EF39: AccumulatedDepreciation_RestatedOpeningBalance | EG39: AccumulatedDepreciation_Depreciation | EH39: DepreciationAdjustments | EI39: AccumulatedDepreciation_Disposal | EJ39: Refurb_Depreciation | EK39: AccumulatedDepreciation_ClosingBalance | EL39: AccumulatedImpairment_OpeningBalance | EM39: AccumulatedImpairment_RestatedOpeningBalance | EN39: AccumulatedImpairmentImpairment | EO39: AccumulatedImpairment_ReversalOfImpairment | EP39: AccumulatedImpairment_Disposal | EQ39: AccumulatedImpairment_ClosingBalance | ER39: CarryingAmount | ES39: Disposal_Proceeds | ET39: Disposal_Profit_Loss | EU39: DonorIDRegistrationNumberParastatalCode | EV39: DonorNameCompanyRegistrationNumberParastatalName | EW39: Date_Donated | EX39: Make | EY39: Model | EZ39: Custom_1 | FA39: Custom_2 | FB39: Custom_3 | FC39: Custom_4 | FD39: Custom_5 | FE39: Custom_6 | FF39: Custom_7 | FG39: Custom_8 | FH39: Custom_9
A40: 2.1 - Asset was revalued on 30 June 2023. The balances at 30 June 2023 = Revaluation reserv = (5,660,048.60), Cost = 12,164,247.00, Acc Dep = (6,020,788.83), RUL = 5534, EUL = 10957.5, Value = 6,143,458.17 Change valuation to R7,500,500.00 | C40: Original values captured | D40: 2024/2025 | E40: 0 | F40: 7424 | G40: RD06804/000 | H40: RD06804 | I40: Bridge Sub Structure | K40: Bridge Sub Structure | O40: Property, Plant and Equipment | P40: Roads Infrastructure | Q40: Roads | R40: Bridge Sub Structure | S40: Revaluation Module | U40: Bridge Sub Structure | V40: Bridge Sub Structure | W40: Property, plant and equipment | X40: Infrastructure assets | Y40: Roads infrastructure | Z40: Road structures | AA40: Road bridges | AB40: New | AC40: Infrastructure | AD40: Non Cash | AE40: EAR (Existing Asset Register) | AF40: 45580 | AG40: 41456 | AH40: 45473 | AL40: 45838.958 | AM40: 45473 | AN40: Lundi Knox Nxawe | AP40: 45473 | AS40: Good | AT40: No | AV40: No | AW40: 12164247 | AX40: 5378818.8 | AY40: 0 | AZ40: 0 | BA40: Straight-line | BB40: 30 | BC40: =BB40*12 -> 360 | BD40: 10957.5 | BE40: =BG40/365 -> 13.158904 | BF40: =BE40*12 -> 157.90685 | BG40: ='2'!$C$40 -> 4803 | BI40: Each | BN40: 1 | BO40: 0 | BP40: 0 | BY40: Zanele Nontando Mbusi | BZ40: 830910xxxxxxx | CA40: Yes | CB40: Important | CC40: Meets requirements | CD40: Normal use | CE40: Good | CF40: Moderate | CG40: Medium | CH40: Mnquma Local Municipality | CI40: Infrastructural Planning & Development | CJ40: Civil Services | CK40: Butterworth | CN40: Ward 1 | CU40: -32.208988 | CV40: 27.794534 | CW40: 1162063.6 | CX40: 0 | DA40: 45107 | DB40: ='2'!$C$9 -> 6143458.2 | DC40: ='2'!$C$8 -> 5660048.6 | DD40: 0 | DE40: 0 | DF40: 0 | DG40: 0 | DH40: 0 | DI40: 0 | DJ40: 0 | DK40: =DC40-DO40 -> 4912398.5 | DL40: 0 | DM40: ='2'!$C$18 -> 374336.43 | DN40: ='2'!$C$31 -> 373313.65 | DO40: =DM40+DN40 -> 747650.08 | DP40: =DK40 -> 4912398.5 | DQ40: Yes | DR40: ='2'!$C$5 -> 12164247 | DS40: ='2'!$C$5 -> 12164247 | DT40: 0 | DU40: 1 | DV40: 0 | DW40: 0 | DX40: 0 | DY40: 0 | DZ40: 0 | EA40: 0 | EB40: 0 | EC40: 0 | ED40: 12164247 | EE40: ='2'!$C$23 -> 6427096.3 | EF40: ='2'!$C$23 -> 6427096.3 | EG40: ='2'!$C$30 -> 405197.3 | EH40: 0 | EI40: 0 | EJ40: 0 | EK40: =EF40+EG40 -> 6832293.6 | EL40: 0 | EM40: 0 | EN40: 0 | EO40: 0 | EP40: 0 | EQ40: 0 | ER40: =ED40-EK40 -> 5331953.4 | ES40: 0 | ET40: 0 | EZ40: Roads | FA40: {8BEA2AE3-F204-4829-8828-5B4A7F3E8976}
A41: 2.1 - Asset was revalued on 30 June 2023. The balances at 30 June 2023 = Revaluation reserv = (5,660,048.60), Cost = 12,164,247.00, Acc Dep = (6,020,788.83), RUL = 5534, EUL = 10957.5, Value = 6,143,458.17 Change valuation to R7,500,500.00 | C41: Corrected values | D41: 2024/2025 | E41: 0 | F41: 7424 | G41: RD06804/000 | H41: RD06804 | I41: Bridge Sub Structure | K41: Bridge Sub Structure | O41: Property, Plant and Equipment | P41: Roads Infrastructure | Q41: Roads | R41: Bridge Sub Structure | S41: Revaluation Module | U41: Bridge Sub Structure | V41: Bridge Sub Structure | W41: Property, plant and equipment | X41: Infrastructure assets | Y41: Roads infrastructure | Z41: Road structures | AA41: Road bridges | AB41: New | AC41: Infrastructure | AD41: Non Cash | AE41: EAR (Existing Asset Register) | AF41: 45580 | AG41: 41456 | AH41: 45473 | AL41: 45838.958 | AM41: 45473 | AN41: Lundi Knox Nxawe | AP41: 45473 | AS41: Good | AT41: No | AV41: No | AW41: 12164247 | AX41: 5378818.8 | AY41: 0 | AZ41: 0 | BA41: Straight-line | BB41: 30 | BC41: =BB41*12 -> 360 | BD41: 10957.5 | BE41: =BG41/365 -> 13.158904 | BF41: =BE41*12 -> 157.90685 | BG41: ='2'!$D$40 -> 4803 | BI41: Each | BN41: 1 | BO41: 0 | BP41: 0 | BY41: Zanele Nontando Mbusi | BZ41: 830910xxxxxxx | CA41: Yes | CB41: Important | CC41: Meets requirements | CD41: Normal use | CE41: Good | CF41: Moderate | CG41: Medium | CH41: Mnquma Local Municipality | CI41: Infrastructural Planning & Development | CJ41: Civil Services | CK41: Butterworth | CN41: Ward 1 | CU41: -32.208988 | CV41: 27.794534 | CW41: 1162063.6 | CX41: 0 | DA41: 45107 | DB41: ='2'!$D$9 -> 7500500 | DC41: ='2'!$D$8 -> 7017090.4 | DD41: 0 | DE41: 0 | DF41: 0 | DG41: 0 | DH41: 0 | DI41: 0 | DJ41: 0 | DK41: =DC41-DO41 -> 6090185.3 | DL41: 0 | DM41: ='2'!$D$18 -> 464086.57 | DN41: ='2'!$D$31 -> 462818.58 | DO41: =DM41+DN41 -> 926905.15 | DP41: =DK41 -> 6090185.3 | DQ41: Yes | DR41: ='2'!$D$5 -> 14851234 | DS41: ='2'!$D$5 -> 14851234 | DT41: 0 | DU41: 1 | DV41: 0 | DW41: 0 | DX41: 0 | DY41: 0 | DZ41: 0 | EA41: 0 | EB41: 0 | EC41: 0 | ED41: =DS41 -> 14851234 | EE41: ='2'!$D$23 -> 7846791.5 | EF41: ='2'!$D$23 -> 7846791.5 | EG41: ='2'!$D$30 -> 494702.23 | EH41: 0 | EI41: 0 | EJ41: 0 | EK41: =EF41+EG41 -> 8341493.8 | EL41: 0 | EM41: 0 | EN41: 0 | EO41: 0 | EP41: 0 | EQ41: 0 | ER41: =ED41-EK41 -> 6509740.2 | ES41: 0 | ET41: 0 | EZ41: Roads | FA41: {8BEA2AE3-F204-4829-8828-5B4A7F3E8976}
A43: Revaluation reserve balance | B43: -5660048.6 | DC43: =DC40-DC41 -> -1357041.8 | DD43: =DD40-DD41 -> 0 | DE43: =DE40-DE41 -> 0 | DF43: =DF40-DF41 -> 0 | DG43: =DG40-DG41 -> 0 | DH43: =DH40-DH41 -> 0 | DI43: =DI40-DI41 -> 0 | DJ43: =DJ40-DJ41 -> 0 | ... DP43: =DP40-DP41 -> -1177786.8 | DR43: =DR40-DR41 -> -2686987 | DS43: =DS40-DS41 -> -2686987 | DT43: =DT40-DT41 -> 0 | DU43: =DU40-DU41 -> 0 | DV43: =DV40-DV41 -> 0 | DW43: =DW40-DW41 -> 0 | DX43: =DX40-DX41 -> 0 | DY43: =DY40-DY41 -> 0 | ... ED43: =ED40-ED41 -> -2686987 | EF43: =EF40-EF41 -> -1419695.3 | EG43: =EG40-EG41 -> -89504.93 | EH43: =EH40-EH41 -> 0 | EI43: =EI40-EI41 -> 0 | EJ43: =EJ40-EJ41 -> 0 | EK43: =EK40-EK41 -> -1509200.2 | ER43: =ER40-ER41 -> -1177786.8
A44: Cost | B44: 12164247
A45: Accumulated Depreciation | B45: 6020788.8 | C45: 7500500 | D45: =ROUND(C45/B47*B46,2) -> 14851234 | E45: =D45-C45 -> 7350734 | F45: =C45-C46 -> 1357041.8
A46: EUL | B46: 10957.5 | C46: =B44-B45 -> 6143458.2 | D46: =ROUND(C46/5534*10957.5,2) -> 12164247 | E46: =D46-C46 -> 6020788.8 | F46: =-B43+F45 -> 7017090.4
A47: RUL | B47: 5534
A48: Carrying value before revaluation | B48: 4318557.7
A49: Revaluation reserve balance before revalaution | B49: -3835148.2
A50: Value adjustment | B50: =C46-B48 -> 1824900.4
A51: Revaluation reserve adjustment | B51: =B43-B49 -> -1824900.4
A53: Description | C53: Current balance | D53: Corrected Balance | E53: Journal - Debit/ (Credit)
A54: Original revaluation entry
A55: Revaluation Reserve | C55: =DC40 -> 5660048.6 | D55: =DC41 -> 7017090.4 | E55: =-D55+C55 -> -1357041.8
A56: Cost | C56: =DS40 -> 12164247 | D56: =DS41 -> 14851234 | E56: =D56-C56 -> 2686987
A57: Accumulated Depreciation | C57: ='2'!$C$6 -> 6020788.8 | D57: ='2'!$D$6 -> 7350734 | E57: =-D57+C57 -> -1329945.1
E58: =SUM(E55:E57) -> 0
A59: RR Offset before 2024
A60: RR Offset 2024 | C60: =DM40 -> 374336.43 | D60: =DM41 -> 464086.57 | E60: =D60-C60 -> 89750.14
A61: RR Offset 2025 | C61: =DN40 -> 373313.65 | D61: =DN41 -> 462818.58 | E61: =D61-C61 -> 89504.93
A62: Accumulated Depreciation - Depreciation Charges before 2024
A63: Accumulated Depreciation - Depreciation Charges 2024 | C63: ='2'!$C$17 -> 406307.43 | D63: ='2'!$D$17 -> 496057.58 | E63: =D63-C63 -> 89750.15
A64: Accumulated Depreciation - Depreciation Charges 2025 | C64: ='2'!$C$30 -> 405197.3 | D64: ='2'!$D$30 -> 494702.23 | E64: =D64-C64 -> 89504.93
A65: Accumulated Surplus - RR Offset | E65: =-E60-E61 -> -179255.07
A66: Accumulated Surplus - Depreciation charges | E66: =-E63-E64 -> -179255.08
D68: FinancialYear | E68: FinancialPeriod | F68: AssetRegisterItemID | G68: MunicipalAssetID | H68: ParentAssetRegisterItem_ID | I68: MainAssetDescription | J68: MainAssetID | K68: AssetDescription | L68: OldBarcode | M68: Barcode | N68: ImageRef | O68: AssetType | P68: AssetCategory | Q68: AssetSubCategory | R68: AssetClass | S68: MeasurementType_ID2 | T68: AssetStatus | U68: CIDMSSubComponentType | V68: CIDMSComponentType | W68: CIDMSAccountingGroup | X68: CIDMSSubAccountingGroup | Y68: CIDMSAssetClass | Z68: CIDMSAssetGroupType | AA68: CIDMSAssetType | AB68: NatureOfAddition | AC68: InfrastructurOrNonInfrastructure | AD68: CashNonCashGeneratingUnit | AE68: FinancialStatus | AF68: TakeOnDate | AG68: AquisitionDate | AH68: System_In_Service_Date | AI68: DisposalDate | AJ68: DisposalReason | AK68: Impairment_Date | AL68: DateModified | AM68: VerificationDate | AN68: VerificationDoneBy | AO68: YearConstructed | AP68: CommisioningDate | AQ68: ConstructionMaterial | AR68: ForecastReplacementYear | AS68: AssetCondition | AT68: InsuranceCover | AU68: InsurancePolicy | AV68: Warranty | AW68: CurrentReplacementCostCRC | AX68: DepreciatedReplacementCostDRC | AY68: AnnualisedMaintenanceCRC | AZ68: AnnualMaintenanceBudgetNeed | BA68: DepreciationMethod | BB68: UsefulLifeYearComponent | BC68: UsefulLifeMonthComponent | BD68: UsefulLifeDaysComponent | BE68: Remaining_Useful_Life_Year | BF68: Remaining_Useful_Life_Months | BG68: Remaining_Useful_Life_Days | BH68: RemainingUsefulllifeAtTakeon | BI68: UOM | BJ68: Dim1 | BK68: Dim2 | BL68: Dim3 | BM68: DimensionQuantity | BN68: Quantity | BO68: Diameter | BP68: Capacity | BQ68: SGNumberChange_ID | BR68: DeedNumber | BS68: ErfNumber | BT68: ErfSizeM2 | BU68: PortionNumber | BV68: UnitNumber | BW68: RegistrationNumber | BX68: SerialNumber | BY68: CustodianName | BZ68: CustodianIdNumber | CA68: BasicMunicipalServices | CB68: CriticalityGrade | CC68: PerformanceGrade | CD68: UtilisationGrade | CE68: InfrastructureHealthGrade | CF68: ConsequenceOfFailure | CG68: Risk | CH68: AssetOwnership | CI68: Department | CJ68: Division | CK68: Town | CL68: StreetName | CM68: Building | CN68: Ward | CO68: Zoning | CP68: FloorArea | CQ68: RoomNumber | CR68: Suburb | CS68: WellKnownTextWKT | CT68: GISID | CU68: Latitude | CV68: Longitude | CW68: FundingSourceAmount | CX68: FundingSourceNumber | CY68: FundType | CZ68: CostOfAddition | DA68: Revaluation_Date | DB68: Revaluation_Value | DC68: Accumulated_Revalutions_Opening_Balance | DD68: Revaluation_Reserve_Impairments_OpeningBalance | DE68: Revaluation_Reserve_Impairments | DF68: Revaluation_Reserve_Impairment_Reversals | DG68: Revaluation_Reserve_Impairments_ClosingBalance | DH68: Revaluation_Reserve_Revaluations | DI68: Revaluation_Reserve_Disposals | DJ68: Refurb_Revaluation | DK68: Accumulated_Revaluation_Closing_Balance | DL68: Movement_In_Revaluation_Reserve | DM68: DepreciationOffsetOpeningBalance | DN68: Depreciation_Offset | DO68: DepreciationOffsetClosingBalance | DP68: Revaluation_Surplus_Deficit | DQ68: Deemed_Cost | DR68: Cost_OpeningBalance | DS68: Cost_RestatedOpeningBalance | DT68: Cost_Acquisitions | DU68: Cost_RisidualValue | DV68: WorkInProgress | DW68: TransferFromAmount | DX68: TransferToAmount | DY68: RefurbishmentCredit | DZ68: RefurbishmentDebit | EA68: Cost_FairValueAdjustment | EB68: Revaluation_Adjustment | EC68: Cost_Disposal | ED68: Cost_ClosingBalance | EE68: AccumulatedDepreciation_OpeningBalance | EF68: AccumulatedDepreciation_RestatedOpeningBalance | EG68: AccumulatedDepreciation_Depreciation | EH68: DepreciationAdjustments | EI68: AccumulatedDepreciation_Disposal | EJ68: Refurb_Depreciation | EK68: AccumulatedDepreciation_ClosingBalance | EL68: AccumulatedImpairment_OpeningBalance | EM68: AccumulatedImpairment_RestatedOpeningBalance | EN68: AccumulatedImpairmentImpairment | EO68: AccumulatedImpairment_ReversalOfImpairment | EP68: AccumulatedImpairment_Disposal | EQ68: AccumulatedImpairment_ClosingBalance | ER68: CarryingAmount | ES68: Disposal_Proceeds | ET68: Disposal_Profit_Loss | EU68: DonorIDRegistrationNumberParastatalCode | EV68: DonorNameCompanyRegistrationNumberParastatalName | EW68: Date_Donated | EX68: Make | EY68: Model | EZ68: Custom_1 | FA68: Custom_2 | FB68: Custom_3 | FC68: Custom_4 | FD68: Custom_5 | FE68: Custom_6 | FF68: Custom_7 | FG68: Custom_8 | FH68: Custom_9
A69: 2.2 - Asset was revalued on 30 June 2023. The balances at 30 June 2023 = Revaluation reserv = (5,660,048.60), Cost = 12,164,247.00, Acc Dep = (6,020,788.83), RUL = 5534, EUL = 10957.5, Value = 6,143,458.17 Change valuation to R5,500,500.00 | C69: Original values captured | D69: 2024/2025 | E69: 0 | F69: 7424 | G69: RD06804/000 | H69: RD06804 | I69: Bridge Sub Structure | K69: Bridge Sub Structure | O69: Property, Plant and Equipment | P69: Roads Infrastructure | Q69: Roads | R69: Bridge Sub Structure | S69: Revaluation Module | U69: Bridge Sub Structure | V69: Bridge Sub Structure | W69: Property, plant and equipment | X69: Infrastructure assets | Y69: Roads infrastructure | Z69: Road structures | AA69: Road bridges | AB69: New | AC69: Infrastructure | AD69: Non Cash | AE69: EAR (Existing Asset Register) | AF69: 45580 | AG69: 41456 | AH69: 45473 | AL69: 45838.958 | AM69: 45473 | AN69: Lundi Knox Nxawe | AP69: 45473 | AS69: Good | AT69: No | AV69: No | AW69: 12164247 | AX69: 5378818.8 | AY69: 0 | AZ69: 0 | BA69: Straight-line | BB69: 30 | BC69: =BB69*12 -> 360 | BD69: 10957.5 | BE69: =BG69/365 -> 13.158904 | BF69: =BE69*12 -> 157.90685 | BG69: ='2'!$C$40 -> 4803 | BI69: Each | BN69: 1 | BO69: 0 | BP69: 0 | BY69: Zanele Nontando Mbusi | BZ69: 830910xxxxxxx | CA69: Yes | CB69: Important | CC69: Meets requirements | CD69: Normal use | CE69: Good | CF69: Moderate | CG69: Medium | CH69: Mnquma Local Municipality | CI69: Infrastructural Planning & Development | CJ69: Civil Services | CK69: Butterworth | CN69: Ward 1 | CU69: -32.208988 | CV69: 27.794534 | CW69: 1162063.6 | CX69: 0 | DA69: 45107 | DB69: ='2'!$C$9 -> 6143458.2 | DC69: ='2'!$C$8 -> 5660048.6 | DD69: 0 | DE69: 0 | DF69: 0 | DG69: 0 | DH69: 0 | DI69: 0 | DJ69: 0 | DK69: =DC69-DO69 -> 4912398.5 | DL69: 0 | DM69: ='2'!$C$18 -> 374336.43 | DN69: ='2'!$C$31 -> 373313.65 | DO69: =DM69+DN69 -> 747650.08 | DP69: =DK69 -> 4912398.5 | DQ69: Yes | DR69: ='2'!$C$5 -> 12164247 | DS69: ='2'!$C$5 -> 12164247 | DT69: 0 | DU69: 1 | DV69: 0 | DW69: 0 | DX69: 0 | DY69: 0 | DZ69: 0 | EA69: 0 | EB69: 0 | EC69: 0 | ED69: 12164247 | EE69: ='2'!$C$23 -> 6427096.3 | EF69: ='2'!$C$23 -> 6427096.3 | EG69: ='2'!$C$30 -> 405197.3 | EH69: 0 | EI69: 0 | EJ69: 0 | EK69: =EF69+EG69 -> 6832293.6 | EL69: 0 | EM69: 0 | EN69: 0 | EO69: 0 | EP69: 0 | EQ69: 0 | ER69: =ED69-EK69 -> 5331953.4 | ES69: 0 | ET69: 0 | EZ69: Roads | FA69: {8BEA2AE3-F204-4829-8828-5B4A7F3E8976}
A70: 2.2 - Asset was revalued on 30 June 2023. The balances at 30 June 2023 = Revaluation reserv = (5,660,048.60), Cost = 12,164,247.00, Acc Dep = (6,020,788.83), RUL = 5534, EUL = 10957.5, Value = 6,143,458.17 Change valuation to R5,500,500.00 | C70: Corrected values | D70: 2024/2025 | E70: 0 | F70: 7424 | G70: RD06804/000 | H70: RD06804 | I70: Bridge Sub Structure | K70: Bridge Sub Structure | O70: Property, Plant and Equipment | P70: Roads Infrastructure | Q70: Roads | R70: Bridge Sub Structure | S70: Revaluation Module | U70: Bridge Sub Structure | V70: Bridge Sub Structure | W70: Property, plant and equipment | X70: Infrastructure assets | Y70: Roads infrastructure | Z70: Road structures | AA70: Road bridges | AB70: New | AC70: Infrastructure | AD70: Non Cash | AE70: EAR (Existing Asset Register) | AF70: 45580 | AG70: 41456 | AH70: 45473 | AL70: 45838.958 | AM70: 45473 | AN70: Lundi Knox Nxawe | AP70: 45473 | AS70: Good | AT70: No | AV70: No | AW70: 12164247 | AX70: 5378818.8 | AY70: 0 | AZ70: 0 | BA70: Straight-line | BB70: 30 | BC70: =BB70*12 -> 360 | BD70: 10957.5 | BE70: =BG70/365 -> 13.158904 | BF70: =BE70*12 -> 157.90685 | BG70: ='2'!$F$40 -> 4803 | BI70: Each | BN70: 1 | BO70: 0 | BP70: 0 | BY70: Zanele Nontando Mbusi | BZ70: 830910xxxxxxx | CA70: Yes | CB70: Important | CC70: Meets requirements | CD70: Normal use | CE70: Good | CF70: Moderate | CG70: Medium | CH70: Mnquma Local Municipality | CI70: Infrastructural Planning & Development | CJ70: Civil Services | CK70: Butterworth | CN70: Ward 1 | CU70: -32.208988 | CV70: 27.794534 | CW70: 1162063.6 | CX70: 0 | DA70: 45107 | DB70: ='2'!$F$9 -> 5500500 | DC70: ='2'!$F$8 -> 5017090.4 | DD70: 0 | DE70: 0 | DF70: 0 | DG70: 0 | DH70: 0 | DI70: 0 | DJ70: 0 | DK70: =DC70-DO70 -> 4354370.3 | DL70: 0 | DM70: ='2'!$F$18 -> 331813.35 | DN70: ='2'!$F$31 -> 330906.76 | DO70: =DM70+DN70 -> 662720.11 | DP70: =DK70 -> 4354370.3 | DQ70: Yes | DR70: ='2'!$F$5 -> 10891169 | DS70: ='2'!$F$5 -> 10891169 | DT70: 0 | DU70: 1 | DV70: 0 | DW70: 0 | DX70: 0 | DY70: 0 | DZ70: 0 | EA70: 0 | EB70: 0 | EC70: 0 | ED70: =DS70 -> 10891169 | EE70: ='2'!$F$23 -> 5754453.3 | EF70: ='2'!$F$23 -> 5754453.3 | EG70: ='2'!$F$30 -> 362790.41 | EH70: 0 | EI70: 0 | EJ70: 0 | EK70: =EF70+EG70 -> 6117243.7 | EL70: 0 | EM70: 0 | EN70: 0 | EO70: 0 | EP70: 0 | EQ70: 0 | ER70: =ED70-EK70 -> 4773925.2 | ES70: 0 | ET70: 0 | EZ70: Roads | FA70: {8BEA2AE3-F204-4829-8828-5B4A7F3E8976}
A72: Revaluation reserve balance | B72: -5660048.6 | DC72: =DC69-DC70 -> 642958.17 | DD72: =DD69-DD70 -> 0 | DE72: =DE69-DE70 -> 0 | DF72: =DF69-DF70 -> 0 | DG72: =DG69-DG70 -> 0 | DH72: =DH69-DH70 -> 0 | DI72: =DI69-DI70 -> 0 | DJ72: =DJ69-DJ70 -> 0 | ... DP72: =DP69-DP70 -> 558028.2 | DR72: =DR69-DR70 -> 1273078.1 | DS72: =DS69-DS70 -> 1273078.1 | DT72: =DT69-DT70 -> 0 | DU72: =DU69-DU70 -> 0 | DV72: =DV69-DV70 -> 0 | DW72: =DW69-DW70 -> 0 | DX72: =DX69-DX70 -> 0 | DY72: =DY69-DY70 -> 0 | ... ED72: =ED69-ED70 -> 1273078.1 | EF72: =EF69-EF70 -> 672642.99 | EG72: =EG69-EG70 -> 42406.89 | EH72: =EH69-EH70 -> 0 | EI72: =EI69-EI70 -> 0 | EJ72: =EJ69-EJ70 -> 0 | EK72: =EK69-EK70 -> 715049.88 | ER72: =ER69-ER70 -> 558028.21
A73: Cost | B73: 12164247
A74: Accumulated Depreciation | B74: 6020788.8 | C74: 5500500 | D74: =ROUND(C74/B76*B75,2) -> 10891169 | E74: =D74-C74 -> 5390668.9 | F74: =C74-C75 -> -642958.17 | G74: =B72-F74 -> -5017090.4
A75: EUL | B75: 10957.5 | C75: =B73-B74 -> 6143458.2 | D75: =ROUND(C75/5534*10957.5,2) -> 12164247 | E75: =D75-C75 -> 6020788.8 | F75: =-B72+F74 -> 5017090.4
A76: RUL | B76: 5534
A77: Carrying value before revaluation | B77: 4318557.7
A78: Revaluation reserve balance before revalaution | B78: -3835148.2
A79: Value adjustment | B79: =C75-B77 -> 1824900.4
A80: Revaluation reserve adjustment | B80: =B72-B78 -> -1824900.4
A82: Description | C82: Current balance | D82: Corrected Balance | E82: Journal - Debit/ (Credit)
A83: Original revaluation entry
A84: Revaluation Reserve | C84: =DC69 -> 5660048.6 | D84: =DC70 -> 5017090.4 | E84: =-D84+C84 -> 642958.17
A85: Cost | C85: =DS69 -> 12164247 | D85: =DS70 -> 10891169 | E85: =D85-C85 -> -1273078.1
A86: Accumulated Depreciation | C86: ='2'!$C$6 -> 6020788.8 | D86: ='2'!$F$6 -> 5390668.9 | E86: =-D86+C86 -> 630119.92
E87: =SUM(E84:E86) -> 0
A88: RR Offset before 2024
A89: RR Offset 2024 | C89: =DM69 -> 374336.43 | D89: =DM70 -> 331813.35 | E89: =D89-C89 -> -42523.08
A90: RR Offset 2025 | C90: =DN69 -> 373313.65 | D90: =DN70 -> 330906.76 | E90: =D90-C90 -> -42406.89
A91: Accumulated Depreciation - Depreciation Charges before 2024
A92: Accumulated Depreciation - Depreciation Charges 2024 | C92: ='2'!$C$17 -> 406307.43 | D92: ='2'!$F$17 -> 363784.36 | E92: =D92-C92 -> -42523.07
A93: Accumulated Depreciation - Depreciation Charges 2025 | C93: ='2'!$C$30 -> 405197.3 | D93: ='2'!$F$30 -> 362790.41 | E93: =D93-C93 -> -42406.89
A94: Accumulated Surplus - RR Offset | E94: =-E89-E90 -> 84929.97
A95: Accumulated Surplus - Depreciation charges | E95: =-E92-E93 -> 84929.96
A97: 3.1 - Asset at deemed cost, acquisition date captured incorrectly at 2024/06/20 instead of 2024/01/15 | C97: Original values captured | D97: 2025/2026 | E97: 0 | F97: 10767 | G97: RD07909/000 | H97: RD07909 | I97: Unpaved Road | K97: Unpaved Road | O97: Property, Plant and Equipment | P97: Roads Infrastructure | Q97: Roads | R97: Unpaved Road | S97: Revaluation Module | U97: Unpaved Road | V97: Unpaved Road | W97: Property, plant and equipment | X97: Infrastructure assets | Y97: Roads infrastructure | Z97: Roads | AA97: Pavements | AB97: New | AC97: Infrastructure | AD97: Non Cash | AE97: EAR (Existing Asset Register) | AF97: =AG97 -> 45463 | AG97: ='3'!$B$7 -> 45463 | AH97: =AG97 -> 45463 | AL97: 45838.958 | AM97: 45473 | AN97: Lundi Knox Nxawe | AP97: 45473 | AS97: Good | AT97: No | AV97: No | AW97: 3046098.5 | AX97: =ER97 -> 2732308.7 | AY97: 0 | AZ97: 0 | BA97: Straight-line | BB97: 10 | BC97: 120 | BD97: 3650 | BE97: =BG97/365 -> 8.969863 | BF97: =BE97*12 -> 107.63836 | BG97: ='3'!$B$28 -> 3274 | BI97: Square Meter | BN97: 1 | BO97: 0 | BP97: 0 | BY97: Zanele Nontando Mbusi | BZ97: 830910xxxxxxx | CA97: Yes | CB97: Important | CC97: Meets requirements | CD97: Normal use | CE97: Very good | CF97: Moderate | CG97: Medium | CH97: Mnquma Local Municipality | CI97: Infrastructural Planning & Development | CJ97: Civil Services | CK97: Butterworth | CN97: Ward 1 | CU97: -32.188584 | CV97: 28.055332 | CW97: 3046098.5 | CX97: 0 | DA97: 1 | DB97: 3036924.8 | DC97: 0 | DD97: 0 | DE97: 0 | DF97: 0 | DG97: 0 | DH97: 0 | DI97: 0 | DJ97: 0 | DK97: 0 | DL97: 0 | DM97: 0 | DN97: 0 | DO97: 0 | DP97: 0 | DQ97: Yes | DR97: 3046098.5 | DS97: 3046098.5 | DT97: 0 | DU97: 1 | DV97: 0 | DW97: 0 | DX97: 0 | DY97: 0 | DZ97: 0 | EA97: 0 | EB97: 0 | EC97: 0 | ED97: =DS97+DT97+DV97-DW97+DX97-DY97+DZ97+EA97+EB97 -> 3046098.5 | EE97: ='3'!$B$15 -> 9180.02 | EF97: ='3'!$B$15 -> 9180.02 | EG97: ='3'!$B$21 -> 304609.75 | EH97: 0 | EI97: 0 | EJ97: 0 | EK97: =EF97+EG97+EH97-EI97-EJ97 -> 313789.77 | EL97: 0 | EM97: 0 | EN97: 0 | EO97: 0 | EP97: 0 | EQ97: =EM97+EN97-EO97-EP97 -> 0 | ER97: =ED97-EK97-EQ97 -> 2732308.7 | ES97: 0 | ET97: 0 | EZ97: Roads | FA97: {539308C0-87C6-4256-BD2D-FD6198DF208C}
A98: 3.1 - Asset at deemed cost, acquisition date captured incorrectly at 2024/06/20 instead of 2024/01/15 | C98: Corrected values | D98: 2025/2026 | E98: 0 | F98: 10767 | G98: RD07909/000 | H98: RD07909 | I98: Unpaved Road | K98: Unpaved Road | O98: Property, Plant and Equipment | P98: Roads Infrastructure | Q98: Roads | R98: Unpaved Road | S98: Revaluation Module | U98: Unpaved Road | V98: Unpaved Road | W98: Property, plant and equipment | X98: Infrastructure assets | Y98: Roads infrastructure | Z98: Roads | AA98: Pavements | AB98: New | AC98: Infrastructure | AD98: Non Cash | AE98: EAR (Existing Asset Register) | AF98: =AG98 -> 45306 | AG98: ='3'!$C$7 -> 45306 | AH98: =AG98 -> 45306 | AL98: 45306 | AM98: 45473 | AN98: Lundi Knox Nxawe | AP98: 45473 | AS98: Good | AT98: No | AV98: No | AW98: 3046098.5 | AX98: =ER98 -> 2601284.8 | AY98: 0 | AZ98: 0 | BA98: Straight-line | BB98: 10 | BC98: 120 | BD98: 3650 | BE98: =BG98/365 -> 8.539726 | BF98: =BE98*12 -> 102.47671 | BG98: ='3'!$C$28 -> 3117 | BI98: Square Meter | BN98: 1 | BO98: 0 | BP98: 0 | BY98: Zanele Nontando Mbusi | BZ98: 830910xxxxxxx | CA98: Yes | CB98: Important | CC98: Meets requirements | CD98: Normal use | CE98: Very good | CF98: Moderate | CG98: Medium | CH98: Mnquma Local Municipality | CI98: Infrastructural Planning & Development | CJ98: Civil Services | CK98: Butterworth | CN98: Ward 1 | CU98: -32.188584 | CV98: 28.055332 | CW98: 3046098.5 | CX98: 0 | DA98: 1 | DB98: 3036924.8 | DC98: 0 | DD98: 0 | DE98: 0 | DF98: 0 | DG98: 0 | DH98: 0 | DI98: 0 | DJ98: 0 | DK98: 0 | DL98: 0 | DM98: 0 | DN98: 0 | DO98: 0 | DP98: 0 | DQ98: Yes | DR98: 3046098.5 | DS98: 3046098.5 | DT98: 0 | DU98: 1 | DV98: 0 | DW98: 0 | DX98: 0 | DY98: 0 | DZ98: 0 | EA98: 0 | EB98: 0 | EC98: 0 | ED98: =DS98+DT98+DV98-DW98+DX98-DY98+DZ98+EA98+EB98 -> 3046098.5 | EE98: ='3'!$C$15 -> 140203.94 | EF98: ='3'!$C$15 -> 140203.94 | EG98: ='3'!$C$21 -> 304609.75 | EH98: 0 | EI98: 0 | EJ98: 0 | EK98: =EF98+EG98+EH98-EI98-EJ98 -> 444813.69 | EL98: 0 | EM98: 0 | EN98: 0 | EO98: 0 | EP98: 0 | EQ98: =EM98+EN98-EO98-EP98 -> 0 | ER98: =ED98-EK98-EQ98 -> 2601284.8 | ES98: 0 | ET98: 0 | EZ98: Roads | FA98: {539308C0-87C6-4256-BD2D-FD6198DF208C}
A99: 3.1 - Asset at deemed cost, acquisition date captured incorrectly at 2024/06/20 instead of 2024/01/15 | C99: Net Correction | DS99: =DS97-DS98 -> 0 | ED99: =ED97-ED98 -> 0 | EE99: =EE97-EE98 -> -131023.92 | EF99: =EF97-EF98 -> -131023.92 | EG99: =EG97-EG98 -> 0 | EK99: =EK97-EK98 -> -131023.92 | ER99: =ER97-ER98 -> 131023.92
A101: Description | C101: Current balance | D101: Corrected Balance | E101: Journal - Debit/ (Credit)
A102: Cost - Roads - Periods before 2024
A103: Cost - Roads - Period 2024 | C103: =DS97 -> 3046098.5 | D103: =DS98 -> 3046098.5 | E103: =D103-C103 -> 0
A104: Cost - Roads - Period 2025
A105: Accumulated Surplus/WIP/Accruals/VAT before 2025 | E105: =-E103 -> 0
A106: Accumulated Surplus/WIP/Accruals/VAT 2025 | E106: =-E104 -> 0
A107: Accumulated Depreciation - Roads - Before 2024
A108: Accumulated Depreciation - Roads - 2024 | C108: ='3'!$B$11 -> 9180.02 | D108: ='3'!$C$11 -> 140203.94 | E108: =C108-D108 -> -131023.92
A109: Accumulated Depreciation - Roads - 2025 | C109: ='3'!$B$21 -> 304609.75 | D109: ='3'!$C$21 -> 304609.75 | E109: =C109-D109 -> 0
A110: Accumulated Surplus - Deprecation Charges before 2025 | C110: =C108 -> 9180.02 | D110: =D108 -> 140203.94 | E110: =D110-C110 -> 131023.92
A111: Accumulated Surplus - Deprecation Charges 2025 | C111: =C109 -> 304609.75 | D111: =D109 -> 304609.75 | E111: =D111-C111 -> 0
A113: 3.2 - Asset at deemed cost, acquisition date captured incorrectly at 2024/06/20 instead of 2024/06/29 | C113: Original values captured | D113: 2025/2026 | E113: 0 | F113: 10767 | G113: RD07909/000 | H113: RD07909 | I113: Unpaved Road | K113: Unpaved Road | O113: Property, Plant and Equipment | P113: Roads Infrastructure | Q113: Roads | R113: Unpaved Road | S113: Revaluation Module | U113: Unpaved Road | V113: Unpaved Road | W113: Property, plant and equipment | X113: Infrastructure assets | Y113: Roads infrastructure | Z113: Roads | AA113: Pavements | AB113: New | AC113: Infrastructure | AD113: Non Cash | AE113: EAR (Existing Asset Register) | AF113: =AG113 -> 45463 | AG113: ='3'!$B$7 -> 45463 | AH113: =AG113 -> 45463 | AL113: 45838.958 | AM113: 45473 | AN113: Lundi Knox Nxawe | AP113: 45473 | AS113: Good | AT113: No | AV113: No | AW113: 3046098.5 | AX113: =ER113 -> 2732308.7 | AY113: 0 | AZ113: 0 | BA113: Straight-line | BB113: 10 | BC113: 120 | BD113: 3650 | BE113: =BG113/365 -> 8.969863 | BF113: =BE113*12 -> 107.63836 | BG113: ='3'!$B$28 -> 3274 | BI113: Square Meter | BN113: 1 | BO113: 0 | BP113: 0 | BY113: Zanele Nontando Mbusi | BZ113: 830910xxxxxxx | CA113: Yes | CB113: Important | CC113: Meets requirements | CD113: Normal use | CE113: Very good | CF113: Moderate | CG113: Medium | CH113: Mnquma Local Municipality | CI113: Infrastructural Planning & Development | CJ113: Civil Services | CK113: Butterworth | CN113: Ward 1 | CU113: -32.188584 | CV113: 28.055332 | CW113: 3046098.5 | CX113: 0 | DA113: 1 | DB113: 3036924.8 | DC113: 0 | DD113: 0 | DE113: 0 | DF113: 0 | DG113: 0 | DH113: 0 | DI113: 0 | DJ113: 0 | DK113: 0 | DL113: 0 | DM113: 0 | DN113: 0 | DO113: 0 | DP113: 0 | DQ113: Yes | DR113: 3046098.5 | DS113: 3046098.5 | DT113: 0 | DU113: 1 | DV113: 0 | DW113: 0 | DX113: 0 | DY113: 0 | DZ113: 0 | EA113: 0 | EB113: 0 | EC113: 0 | ED113: =DS113+DT113+DV113-DW113+DX113-DY113+DZ113+EA113+EB113 -> 3046098.5 | EE113: ='3'!$B$15 -> 9180.02 | EF113: ='3'!$B$15 -> 9180.02 | EG113: ='3'!$B$21 -> 304609.75 | EH113: 0 | EI113: 0 | EJ113: 0 | EK113: =EF113+EG113+EH113-EI113-EJ113 -> 313789.77 | EL113: 0 | EM113: 0 | EN113: 0 | EO113: 0 | EP113: 0 | EQ113: =EM113+EN113-EO113-EP113 -> 0 | ER113: =ED113-EK113-EQ113 -> 2732308.7 | ES113: 0 | ET113: 0 | EZ113: Roads | FA113: {539308C0-87C6-4256-BD2D-FD6198DF208C}
A114: 3.2 - Asset at deemed cost, acquisition date captured incorrectly at 2024/06/20 instead of 2024/06/29 | C114: Corrected values | D114: 2025/2026 | E114: 0 | F114: 10767 | G114: RD07909/000 | H114: RD07909 | I114: Unpaved Road | K114: Unpaved Road | O114: Property, Plant and Equipment | P114: Roads Infrastructure | Q114: Roads | R114: Unpaved Road | S114: Revaluation Module | U114: Unpaved Road | V114: Unpaved Road | W114: Property, plant and equipment | X114: Infrastructure assets | Y114: Roads infrastructure | Z114: Roads | AA114: Pavements | AB114: New | AC114: Infrastructure | AD114: Non Cash | AE114: EAR (Existing Asset Register) | AF114: =AG114 -> 45472 | AG114: ='3'!$D$7 -> 45472 | AH114: =AG114 -> 45472 | AL114: 45306 | AM114: 45473 | AN114: Lundi Knox Nxawe | AP114: 45473 | AS114: Good | AT114: No | AV114: No | AW114: 3046098.5 | AX114: =ER114 -> 2739819.7 | AY114: 0 | AZ114: 0 | BA114: Straight-line | BB114: 10 | BC114: 120 | BD114: 3650 | BE114: =BG114/365 -> 8.9945205 | BF114: =BE114*12 -> 107.93425 | BG114: ='3'!$D$28 -> 3283 | BI114: Square Meter | BN114: 1 | BO114: 0 | BP114: 0 | BY114: Zanele Nontando Mbusi | BZ114: 830910xxxxxxx | CA114: Yes | CB114: Important | CC114: Meets requirements | CD114: Normal use | CE114: Very good | CF114: Moderate | CG114: Medium | CH114: Mnquma Local Municipality | CI114: Infrastructural Planning & Development | CJ114: Civil Services | CK114: Butterworth | CN114: Ward 1 | CU114: -32.188584 | CV114: 28.055332 | CW114: 3046098.5 | CX114: 0 | DA114: 1 | DB114: 3036924.8 | DC114: 0 | DD114: 0 | DE114: 0 | DF114: 0 | DG114: 0 | DH114: 0 | DI114: 0 | DJ114: 0 | DK114: 0 | DL114: 0 | DM114: 0 | DN114: 0 | DO114: 0 | DP114: 0 | DQ114: Yes | DR114: 3046098.5 | DS114: 3046098.5 | DT114: 0 | DU114: 1 | DV114: 0 | DW114: 0 | DX114: 0 | DY114: 0 | DZ114: 0 | EA114: 0 | EB114: 0 | EC114: 0 | ED114: =DS114+DT114+DV114-DW114+DX114-DY114+DZ114+EA114+EB114 -> 3046098.5 | EE114: ='3'!$D$15 -> 1669.09 | EF114: ='3'!$D$15 -> 1669.09 | EG114: ='3'!$D$21 -> 304609.75 | EH114: 0 | EI114: 0 | EJ114: 0 | EK114: =EF114+EG114+EH114-EI114-EJ114 -> 306278.84 | EL114: 0 | EM114: 0 | EN114: 0 | EO114: 0 | EP114: 0 | EQ114: =EM114+EN114-EO114-EP114 -> 0 | ER114: =ED114-EK114-EQ114 -> 2739819.7 | ES114: 0 | ET114: 0 | EZ114: Roads | FA114: {539308C0-87C6-4256-BD2D-FD6198DF208C}
A115: 3.2 - Asset at deemed cost, acquisition date captured incorrectly at 2024/06/20 instead of 2024/06/29 | C115: Net Correction | DS115: =DS113-DS114 -> 0 | ED115: =ED113-ED114 -> 0 | EE115: =EE113-EE114 -> 7510.93 | EF115: =EF113-EF114 -> 7510.93 | EG115: =EG113-EG114 -> 0 | EK115: =EK113-EK114 -> 7510.93 | ER115: =ER113-ER114 -> -7510.93
A117: Description | C117: Current balance | D117: Corrected Balance | E117: Journal - Debit/ (Credit)
A118: Cost - Roads - Periods before 2024
...

Sheet 1
C2: 1.1 | D2: 1.2
B3: Normal | C3: Cost increase due to incorrect t treatment of WIP, Retentions, VAT, etc. Cost increases from R3,046,098.51 to R3,807,623.14 | D3: Cost decrease due to incorrect t treatment of WIP, Retentions, VAT, etc. Cost decreases from R3,046,098.51 to R2,284,573.88
A5: Cost | B5: 3046098.5 | C5: 3807623.1 | D5: 2284573.9
A6: EUL | B6: 3650 | C6: 3650 | D6: 3650
A7: Acquisition date | B7: 45306 | C7: 45306 | D7: 45306
A8: Residual Value | B8: 1 | C8: 1 | D8: 1
A9: Year 1 | B9: 45473 | C9: 45473 | D9: 45473
A10: Days in use at 30 June 2024 | B10: =B9-B7+1 -> 168 | C10: =C9-C7+1 -> 168 | D10: =D9-D7+1 -> 168
A11: Accumulated Depreciation 20 June 2024 | B11: =ROUND((B5-B8)/B6*B10,2) -> 140203.94 | C11: =ROUND((C5-C8)/C6*C10,2) -> 175254.94 | D11: =ROUND((D5-D8)/D6*D10,2) -> 105152.94
A14: Cost | B14: =B5 -> 3046098.5 | C14: =C5 -> 3807623.1 | D14: =D5 -> 2284573.9
A15: Accumulated Depreciation | B15: =B11 -> 140203.94 | C15: =C11 -> 175254.94 | D15: =D11 -> 105152.94
A16: Accumulated Impairment
A17: Carrying Value | B17: =B14-B15-B16 -> 2905894.6 | C17: =C14-C15-C16 -> 3632368.2 | D17: =D14-D15-D16 -> 2179420.9
A19: RUL | B19: =B6-B10 -> 3482 | C19: =C6-C10 -> 3482 | D19: =D6-D10 -> 3482
A21: Depreciation 2025 | B21: =ROUND((B17-B8)/B19*365,2) -> 304609.75 | C21: =ROUND((C17-C8)/C19*365,2) -> 380762.21 | D21: =ROUND((D17-D8)/D19*365,2) -> 228457.29
A23: Cost | B23: =B5 -> 3046098.5 | C23: =C5 -> 3807623.1 | D23: =D5 -> 2284573.9
A24: Accumulated Depreciation | B24: =B15+B21 -> 444813.69 | C24: =C15+C21 -> 556017.15 | D24: =D15+D21 -> 333610.23
A25: Accumulated Impairment
A26: Carrying Value | B26: =B23-B24-B25 -> 2601284.8 | C26: =C23-C24-C25 -> 3251606 | D26: =D23-D24-D25 -> 1950963.6
B28: =B19-365 -> 3117 | C28: =C19-365 -> 3117 | D28: =D19-365 -> 3117

Sheet 2
D2: 2.1 | F2: 2.2
B3: Before revaluation | C3: Revaluation 30 June 2023 | D3: Asset was revalued on 30 June 2023. The balances at 30 June 2023 = Revaluation reserv = (5,660,048.60), Cost = 12,164,247.00, Acc Dep = (6,020,788.83), RUL = 5534, EUL = 10957.5, Value = 6,143,458.17 Change valuation to R7,500,500.00 | F3: Asset was revalued on 30 June 2023. The balances at 30 June 2023 = Revaluation reserv = (5,660,048.60), Cost = 12,164,247.00, Acc Dep = (6,020,788.83), RUL = 5534, EUL = 10957.5, Value = 6,143,458.17 Change valuation to R5,500,500.00
A5: Cost | B5: 14067804 | C5: 12164247 | D5: =ROUND(D9/D12*D11,2) -> 14851234 | E5: =D5-C5 -> 2686987 | F5: =ROUND(F9/F12*F11,2) -> 10891169 | G5: =F5-C5 -> -1273078.1
A6: Accumulated depreciation | B6: 9749246.1 | C6: 6020788.8 | D6: =D5-D9 -> 7350734 | E6: =-D6+C6 -> -1329945.1 | F6: =F5-F9 -> 5390668.9 | G6: =-F6+C6 -> 630119.92
A7: Accumulated impairment losses
A8: Revaluation reserve | B8: 3835148.2 | C8: 5660048.6 | D8: =D9-C9+C8 -> 7017090.4 | E8: =-D8+C8 -> -1357041.8 | F8: =F9-C9+C8 -> 5017090.4 | G8: =-F8+C8 -> 642958.17
A9: Carrying Value | B9: =B5-B6 -> 4318557.7 | C9: =C5-C6 -> 6143458.2 | D9: 7500500 | E9: =SUM(E5:E8) -> 0 | F9: 5500500 | G9: =SUM(G5:G8) -> 0
A11: EUL | C11: 10957.5 | D11: 10957.5 | F11: 10957.5
A12: RUL | C12: 5534 | D12: 5534 | F12: 5534
A13: Residual Value | C13: 1 | D13: 1 | F13: 1
A14: Depreciation start date | C14: 45108 | D14: 45108 | F14: 45108
A15: Year 1 | C15: 45473 | D15: 45473 | F15: 45473
A16: Day is use 30 June 2024 | C16: =C15-C14+1 -> 366 | D16: =D15-D14+1 -> 366 | F16: =F15-F14+1 -> 366
A17: Accumulated Depreciation 30 June 2024 | C17: =ROUND((C9-C13)/C12*C16,2) -> 406307.43 | D17: =ROUND((D9-D13)/D12*D16,2) -> 496057.58 | F17: =ROUND((F9-F13)/F12*F16,2) -> 363784.36
A18: Depreciation offset 30 June 2024 | C18: =ROUND(C8/C12*C16,2) -> 374336.43 | D18: =ROUND(D8/D12*D16,2) -> 464086.57 | F18: =ROUND(F8/F12*F16,2) -> 331813.35
A22: Cost | C22: =C5 -> 12164247 | D22: =D5 -> 14851234 | F22: =F5 -> 10891169
A23: Accumulated Depreciation | C23: =C6+C17 -> 6427096.3 | D23: =D6+D17 -> 7846791.5 | F23: =F6+F17 -> 5754453.3
A24: Accumulated Impairment
A25: Carrying Value | C25: =C22-C23-C24 -> 5737150.7 | D25: =D22-D23-D24 -> 7004442.4 | F25: =F22-F23-F24 -> 5136715.6
A26: Revaluation Reserve | C26: =C8-C18 -> 5285712.2 | D26: =D8-D18 -> 6553003.9 | F26: =F8-F18 -> 4685277.1
A28: RUL | C28: =C12-C16 -> 5168 | D28: =D12-D16 -> 5168 | F28: =F12-F16 -> 5168
A30: Depreciation 2025 | C30: =ROUND((C25-C13)/C28*365,2) -> 405197.3 | D30: =ROUND((D25-D13)/D28*365,2) -> 494702.23 | F30: =ROUND((F25-F13)/F28*365,2) -> 362790.41
A31: Depreciation offset 2025 | C31: =ROUND(C26/C28*365,2) -> 373313.65 | D31: =ROUND(D26/D28*365,2) -> 462818.58 | F31: =ROUND(F26/F28*365,2) -> 330906.76
A34: Cost | C34: =C22 -> 12164247 | D34: =D22 -> 14851234 | F34: =F22 -> 10891169
A35: Accumulated Depreciation | C35: =C23+C30 -> 6832293.6 | D35: =D23+D30 -> 8341493.8 | F35: =F23+F30 -> 6117243.7
A36: Accumulated Impairment
A37: Carrying Value | C37: =C34-C35-C36 -> 5331953.4 | D37: =D34-D35-D36 -> 6509740.2 | F37: =F34-F35-F36 -> 4773925.2
A38: Revaluation Reserve | C38: =C26-C31 -> 4912398.5 | D38: =D26-D31 -> 6090185.3 | F38: =F26-F31 -> 4354370.3
C40: =C28-365 -> 4803 | D40: =D28-365 -> 4803 | F40: =F28-365 -> 4803

Sheet 3
C2: 3.1 | D2: 3.2
B3: Normal | C3: Asset at deemed cost, acquisition date captured incorrectly at 2024/06/20 instead of 2024/01/15 | D3: Cost decrease due to incorrect t treatment of WIP, Retentions, VAT, etc. Cost decreases from R3,046,098.51 to R2,284,573.88
A5: Cost | B5: 3046098.5 | C5: 3046098.5 | D5: 3046098.5
A6: EUL | B6: 3650 | C6: 3650 | D6: 3650
A7: Acquisition date | B7: 45463 | C7: 45306 | D7: 45472
A8: Residual Value | B8: 1 | C8: 1 | D8: 1
A9: Year 1 | B9: 45473 | C9: 45473 | D9: 45473
A10: Days in use at 30 June 2024 | B10: =B9-B7+1 -> 11 | C10: =C9-C7+1 -> 168 | D10: =D9-D7+1 -> 2
A11: Accumulated Depreciation 20 June 2024 | B11: =ROUND((B5-B8)/B6*B10,2) -> 9180.02 | C11: =ROUND((C5-C8)/C6*C10,2) -> 140203.94 | D11: =ROUND((D5-D8)/D6*D10,2) -> 1669.09
A14: Cost | B14: =B5 -> 3046098.5 | C14: =C5 -> 3046098.5 | D14: =D5 -> 3046098.5
A15: Accumulated Depreciation | B15: =B11 -> 9180.02 | C15: =C11 -> 140203.94 | D15: =D11 -> 1669.09
A16: Accumulated Impairment
A17: Carrying Value | B17: =B14-B15-B16 -> 3036918.5 | C17: =C14-C15-C16 -> 2905894.6 | D17: =D14-D15-D16 -> 3044429.4
A19: RUL | B19: =B6-B10 -> 3639 | C19: =C6-C10 -> 3482 | D19: =D6-D10 -> 3648
A21: Depreciation 2025 | B21: =ROUND((B17-B8)/B19*365,2) -> 304609.75 | C21: =ROUND((C17-C8)/C19*365,2) -> 304609.75 | D21: =ROUND((D17-D8)/D19*365,2) -> 304609.75
A23: Cost | B23: =B5 -> 3046098.5 | C23: =C5 -> 3046098.5 | D23: =D5 -> 3046098.5
A24: Accumulated Depreciation | B24: =B15+B21 -> 313789.77 | C24: =C15+C21 -> 444813.69 | D24: =D15+D21 -> 306278.84
A25: Accumulated Impairment
A26: Carrying Value | B26: =B23-B24-B25 -> 2732308.7 | C26: =C23-C24-C25 -> 2601284.8 | D26: =D23-D24-D25 -> 2739819.7
B28: =B19-365 -> 3274 | C28: =C19-365 -> 3117 | D28: =D19-365 -> 3283

Sheet 4
B3: Before | C3: Asset not recognised - Newly identified, Donated asset, etc - FV - take on date 20 June 2024, deemed cost R3,046,098.51, RUL at take on is 2950 days
A5: Cost | C5: 3046098.5
A6: EUL | C6: 2950
A7: Acquisition date | C7: 45463
A8: Residual Value | C8: 1
A9: Year 1 | C9: 45473
A10: Days in use at 30 June 2024 | C10: =C9-C7+1 -> 11
A11: Accumulated Depreciation 20 June 2024 | C11: =ROUND((C5-C8)/C6*C10,2) -> 11358.33
A14: Cost | B14: =B5 -> 0 | C14: =C5 -> 3046098.5
A15: Accumulated Depreciation | B15: =B11 -> 0 | C15: =C11 -> 11358.33
A16: Accumulated Impairment
A17: Carrying Value | B17: =B14-B15-B16 -> 0 | C17: =C14-C15-C16 -> 3034740.2
A19: RUL | C19: =C6-C10 -> 2939
A21: Depreciation 2025 | C21: =ROUND((C17-C8)/C19*365,2) -> 376890.03
A23: Cost | C23: =C5 -> 3046098.5
A24: Accumulated Depreciation | C24: =C15+C21 -> 388248.36
A25: Accumulated Impairment
A26: Carrying Value | B26: =B23-B24-B25 -> 0 | C26: =C23-C24-C25 -> 2657850.1
C28: =C19-365 -> 2574

Sheet 5
C2: 5.1 & 5.2 | D2: 5.2
B3: Normal | C3: Residual value not captured - Should be R301,609.85 | D3: Residual value captured as R500,100.00 instead of R304,610.00
A5: Cost | B5: 3046098.5 | C5: 3046098.5 | D5: 3046098.5
A6: EUL | B6: 3650 | C6: 3650 | D6: 3650
A7: Acquisition date | B7: 45463 | C7: 45463 | D7: 45463
A8: Residual Value | B8: 1 | C8: 304609.85 | D8: 500100
A9: Year 1 | B9: 45473 | C9: 45473 | D9: 45473
A10: Days in use at 30 June 2024 | B10: =B9-B7+1 -> 11 | C10: =C9-C7+1 -> 11 | D10: =D9-D7+1 -> 11
A11: Accumulated Depreciation 20 June 2024 | B11: =ROUND((B5-B8)/B6*B10,2) -> 9180.02 | C11: =ROUND((C5-C8)/C6*C10,2) -> 8262.02 | D11: =ROUND((D5-D8)/D6*D10,2) -> 7672.87
A14: Cost | B14: =B5 -> 3046098.5 | C14: =C5 -> 3046098.5 | D14: =D5 -> 3046098.5
A15: Accumulated Depreciation | B15: =B11 -> 9180.02 | C15: =C11 -> 8262.02 | D15: =D11 -> 7672.87
A16: Accumulated Impairment
A17: Carrying Value | B17: =B14-B15-B16 -> 3036918.5 | C17: =C14-C15-C16 -> 3037836.5 | D17: =D14-D15-D16 -> 3038425.6
A19: RUL | B19: =B6-B10 -> 3639 | C19: =C6-C10 -> 3639 | D19: =D6-D10 -> 3639
A21: Depreciation 2025 | B21: =ROUND((B17-B8)/B19*365,2) -> 304609.75 | C21: =ROUND((C17-C8)/C19*365,2) -> 274148.87 | D21: =ROUND((D17-D8)/D19*365,2) -> 254599.85
A23: Cost | B23: =B5 -> 3046098.5 | C23: =C5 -> 3046098.5 | D23: =D5 -> 3046098.5
A24: Accumulated Depreciation | B24: =B15+B21 -> 313789.77 | C24: =C15+C21 -> 282410.89 | D24: =D15+D21 -> 262272.72
A25: Accumulated Impairment
A26: Carrying Value | B26: =B23-B24-B25 -> 2732308.7 | C26: =C23-C24-C25 -> 2763687.6 | D26: =D23-D24-D25 -> 2783825.8
B28: =B19-365 -> 3274 | C28: =C19-365 -> 3274 | D28: =D19-365 -> 3274

Sheet 6
C2: 6.1 | E2: 6.2 | F2: 6.3
B3: Normal | C3: Impaired tp 1200000 | E3: Impaired tp 1400000 | F3: Impaired tp 1000000
A5: Cost | B5: 3046098.5 | C5: 3046098.5 | E5: 3046098.5 | F5: 3046098.5
A6: EUL | B6: 3650 | C6: 3650 | E6: 3650 | F6: 3650
A7: Acquisition date | B7: 45306 | C7: 45306 | E7: 45306 | F7: 45306
A8: Residual Value | B8: 1 | C8: 1 | E8: 1 | F8: 1
A9: Impairment date | B9: 45463 | C9: 45463 | E9: 45463 | F9: 45463
B10: 45473 | C10: 45473 | E10: 45473 | F10: 45473
A11: Day is use 20 June 2024 | B11: =B9-B7+1 -> 158 | C11: =C9-C7+1 -> 158 | E11: =E9-E7+1 -> 158 | F11: =F9-F7+1 -> 158
A12: Days in use 20 June to 30 June | B12: =B10-B7+1-B11 -> 10 | C12: =C10-C7+1-C11 -> 10 | E12: =E10-E7+1-E11 -> 10 | F12: =F10-F7+1-F11 -> 10
A13: Accumulated Depreciation 20 June 2024 | B13: =ROUND((B5-B8)/B6*B11,2) -> 131858.47 | C13: =ROUND((C5-C8)/C6*C11,2) -> 131858.47 | E13: =ROUND((E5-E8)/E6*E11,2) -> 131858.47 | F13: =ROUND((F5-F8)/F6*F11,2) -> 131858.47
A15: Impairment | C15: =C5-C13-1200000 -> 1714240 | E15: =E5-E13-1400000 -> 1514240 | F15: =F5-F13-1000000 -> 1914240
A16: RUL after impairment | C16: 730 | E16: 730 | F16: 730
A18: Depreciation 21 June to 30 June | B18: =ROUND((B5-B8)/B6*B12,2) -> 8345.47 | C18: =ROUND((C5-C13-C15-C8)/C16*C12,2) -> 16438.34 | E18: =ROUND((E5-E13-E15-E8)/E16*E12,2) -> 19178.07 | F18: =ROUND((F5-F13-F15-F8)/F16*F12,2) -> 13698.62
A21: Cost | B21: =B5 -> 3046098.5 | C21: =C5 -> 3046098.5 | E21: =E5 -> 3046098.5 | F21: =F5 -> 3046098.5
A22: Accumulated Depreciation | B22: =B13+B18 -> 140203.94 | C22: =C13+C18 -> 148296.81 | E22: =E13+E18 -> 151036.54 | F22: =F13+F18 -> 145557.09
A23: Accumulated Impairment | C23: =C15 -> 1714240 | E23: =E15 -> 1514240 | F23: =F15 -> 1914240
A24: Carrying Value | B24: =B21-B22-B23 -> 2905894.6 | C24: =C21-C22-C23 -> 1183561.7 | E24: =E21-E22-E23 -> 1380821.9 | F24: =F21-F22-F23 -> 986301.38
A26: RUL | B26: =B6-B11-B12 -> 3482 | C26: =C16-C12 -> 720 | E26: =E16-E12 -> 720 | F26: =F16-F12 -> 720
A28: Depreciation 2025 | B28: =ROUND((B24-B8)/B26*365,2) -> 304609.75 | C28: =ROUND((C24-C8)/C26*365,2) -> 599999.5 | E28: =ROUND((E24-E8)/E26*365,2) -> 699999.5 | F28: =ROUND((F24-F8)/F26*365,2) -> 499999.5
A32: Cost | B32: =B5 -> 3046098.5 | C32: =C5 -> 3046098.5 | E32: =E5 -> 3046098.5 | F32: =F5 -> 3046098.5
A33: Accumulated Depreciation | B33: =B22+B28 -> 444813.69 | C33: =C22+C28 -> 748296.31 | E33: =E22+E28 -> 851036.04 | F33: =F22+F28 -> 645556.59
A34: Accumulated Impairment | C34: =C23 -> 1714240 | E34: =E23 -> 1514240 | F34: =F23 -> 1914240
A35: Carrying Value | B35: =B32-B33-B34 -> 2601284.8 | C35: =C32-C33-C34 -> 583562.16 | E35: =E32-E33-E34 -> 680822.43 | F35: =F32-F33-F34 -> 486301.88
B37: =B26-365 -> 3117 | C37: =C26-365 -> 355 | E37: =E26-365 -> 355 | F37: =F26-365 -> 355

Sheet 7.1
B3: Before revaluation | C3: Revaluation 30 June 2023 | D3: Before Impairment | E3: Impaired to R3m on 20 June 2024
A5: Cost | B5: 14067804 | C5: 12164247
A6: Accumulated depreciation | B6: 9749246.1 | C6: 6020788.8
A7: Accumulated impairment losses
A8: Revaluation reserve | B8: 3835148.2 | C8: 5660048.6
A9: Carrying Value | B9: =B5-B6 -> 4318557.7 | C9: =C5-C6 -> 6143458.2
A11: EUL | C11: 10957.5
A12: RUL | C12: 5534
A13: RUL after impairment | C13: 2192
A14: Residual Value | C14: 1
A15: Depreciation start date | C15: 45108
A16: Impairment date | C16: 45463
C17: 45473
A18: Day is use 20 June 2024 | C18: =C16-C15+1 -> 356
A19: Days in use 20 June to 30 June | C19: =C17-C15+1-C18 -> 10
A20: Accumulated Depreciation 20 June 2024 | D20: =ROUND((C9-C14)/C12*C18,2) -> 395206.14 | E20: =ROUND((C9-C14)/C12*C18,2) -> 395206.14
A21: Depreciation offset 20 June 2024 | D21: =ROUND(C8/C12*C18,2) -> 364108.66 | E21: =ROUND(C8/C12*C18,2) -> 364108.66
A23: Impairment | E23: =-3000000+(C9-E20) -> 2748252
A25: Depreciation 21 June to 30 June | D25: =ROUND((C9-C14-D20)/C12*C19,2) -> 10387.15 | E25: =ROUND((C9-C14-E20-E23)/C13*C19,2) -> 13686.13
A26: Depreciation offset 21 June to 30 June | D26: =ROUND(C8/C12*C19,2) -> 10227.77 | E26: =ROUND((C8-E21-E23)/C13*C19,2) -> 11622.66
A29: Cost | D29: =C5 -> 12164247 | E29: =C5 -> 12164247
A30: Accumulated Depreciation | D30: =C6+D20+D25 -> 6426382.1 | E30: =C6+E20+E25 -> 6429681.1
A31: Accumulated Impairment | E31: =E23 -> 2748252
A32: Carrying Value | D32: =D29-D30-D31 -> 5737864.9 | E32: =E29-E30-E31 -> 2986313.9
A33: Revaluation Reserve | D33: =C8-D21-D26 -> 5285712.2 | E33: =C8-E21-E23-E26 -> 2536065.3
A35: RUL | D35: =C12-C18-C19 -> 5168 | E35: =C13-C19 -> 2182
A37: Depreciation 2025 | D37: =ROUND((D32-C14)/D35*365,2) -> 405247.74 | E37: =ROUND((E32-C14)/E35*365,2) -> 499543.63
A38: Depreciation offset 2025 | D38: =ROUND(D33/D35*365,2) -> 373313.65 | E38: =ROUND(E33/E35*365,2) -> 424227.23
A41: Cost | D41: =D29 -> 12164247 | E41: =C5 -> 12164247
A42: Accumulated Depreciation | D42: =D30+D37 -> 6831629.9 | E42: =E30+E37 -> 6929224.7
A43: Accumulated Impairment | E43: =E31 -> 2748252
A44: Carrying Value | D44: =D41-D42-D43 -> 5332617.1 | E44: =E41-E42-E43 -> 2486770.2
A45: Revaluation Reserve | D45: =D33-D38 -> 4912398.5 | E45: =E33-E38 -> 2111838
D47: =D35-365 -> 4803 | E47: =E35-365 -> 1817

Sheet 7.2
B3: Before revaluation | C3: Revaluation 30 June 2023 | D3: Impaired to R3m on 20 June 2024 | E3: Impaired to R2m on 20 June 2024
A5: Cost | B5: 14067804 | C5: 12164247
A6: Accumulated depreciation | B6: 9749246.1 | C6: 6020788.8
A7: Accumulated impairment losses
A8: Revaluation reserve | B8: 3835148.2 | C8: 5660048.6
A9: Carrying Value | B9: =B5-B6 -> 4318557.7 | C9: =C5-C6 -> 6143458.2
A11: Impaired to | D11: 3000000 | E11: 2000000
A12: EUL | C12: 10957.5
A13: RUL | C13: 5534
A14: RUL after impairment | C14: 2192
A15: Residual Value | C15: 1
A16: Depreciation start date | C16: 45108
A17: Impairment date | C17: 45463
C18: 45473
A19: Day is use 20 June 2024 | C19: =C17-C16+1 -> 356
A20: Days in use 20 June to 30 June | C20: =C18-C16+1-C19 -> 10
A21: Accumulated Depreciation 20 June 2024 | D21: =ROUND((C9-C15)/C13*C19,2) -> 395206.14 | E21: =ROUND((C9-C15)/C13*C19,2) -> 395206.14
A22: Depreciation offset 20 June 2024 | D22: =ROUND(C8/C13*C19,2) -> 364108.66 | E22: =ROUND(C8/C13*C19,2) -> 364108.66
A24: Impairment | D24: =-D11+(C9-D21) -> 2748252 | E24: =-E11+(C9-E21) -> 3748252
A26: Depreciation 21 June to 30 June | D26: =ROUND((C9-C15-D21-D24)/C14*C20,2) -> 13686.13 | E26: =ROUND((C9-C15-E21-E24)/C14*C20,2) -> 9124.08
A27: Depreciation offset 21 June to 30 June | D27: =ROUND((C8-D22-D24)/C14*C20,2) -> 11622.66 | E27: =ROUND((C8-E22-E24)/C14*C20,2) -> 7060.62
A30: Cost | D30: =C5 -> 12164247 | E30: =C5 -> 12164247
A31: Accumulated Depreciation | D31: =C6+D21+D26 -> 6429681.1 | E31: =C6+E21+E26 -> 6425119.1
A32: Accumulated Impairment | D32: =D24 -> 2748252 | E32: =E24 -> 3748252
A33: Carrying Value | D33: =D30-D31-D32 -> 2986313.9 | E33: =E30-E31-E32 -> 1990875.9
A34: Revaluation Reserve | D34: =C8-D22-D24-D27 -> 2536065.3 | E34: =C8-E22-E24-E27 -> 1540627.3
A36: RUL | D36: =C14-C20 -> 2182 | E36: =C14-C20 -> 2182
A38: Depreciation 2025 | D38: =ROUND((D33-C15)/D36*365,2) -> 499543.63 | E38: =ROUND((E33-C15)/E36*365,2) -> 333029.03
A39: Depreciation offset 2025 | D39: =ROUND(D34/D36*365,2) -> 424227.23 | E39: =ROUND(E34/E36*365,2) -> 257712.63
A42: Cost | D42: =C5 -> 12164247 | E42: =C5 -> 12164247
A43: Accumulated Depreciation | D43: =D31+D38 -> 6929224.7 | E43: =E31+E38 -> 6758148.1
A44: Accumulated Impairment | D44: =D32 -> 2748252 | E44: =E32 -> 3748252
A45: Carrying Value | D45: =D42-D43-D44 -> 2486770.2 | E45: =E42-E43-E44 -> 1657846.9
A46: Revaluation Reserve | D46: =D34-D39 -> 2111838 | E46: =E34-E39 -> 1282914.7
D48: =D36-365 -> 1817 | E48: =E36-365 -> 1817

Sheet 7.3
B3: Before revaluation | C3: Revaluation 30 June 2023 | D3: Impaired to R3m on 20 June 2024 | E3: Impaired to R4m on 20 June 2024
A5: Cost | B5: 14067804 | C5: 12164247
A6: Accumulated depreciation | B6: 9749246.1 | C6: 6020788.8
A7: Accumulated impairment losses
A8: Revaluation reserve | B8: 3835148.2 | C8: 5660048.6
A9: Carrying Value | B9: =B5-B6 -> 4318557.7 | C9: =C5-C6 -> 6143458.2
A11: Impaired to | D11: 3000000 | E11: 4000000
A12: EUL | C12: 10957.5
A13: RUL | C13: 5534
A14: RUL after impairment | C14: 2192
A15: Residual Value | C15: 1
A16: Depreciation start date | C16: 45108
A17: Impairment date | C17: 45463
C18: 45473
A19: Day is use 20 June 2024 | C19: =C17-C16+1 -> 356
A20: Days in use 20 June to 30 June | C20: =C18-C16+1-C19 -> 10
A21: Accumulated Depreciation 20 June 2024 | D21: =ROUND((C9-C15)/C13*C19,2) -> 395206.14 | E21: =ROUND((C9-C15)/C13*C19,2) -> 395206.14
A22: Depreciation offset 20 June 2024 | D22: =ROUND(C8/C13*C19,2) -> 364108.66 | E22: =ROUND(C8/C13*C19,2) -> 364108.66
A24: Impairment | D24: =-D11+(C9-D21) -> 2748252 | E24: =-E11+(C9-E21) -> 1748252
A26: Depreciation 21 June to 30 June | D26: =ROUND((C9-C15-D21-D24)/C14*C20,2) -> 13686.13 | E26: =ROUND((C9-C15-E21-E24)/C14*C20,2) -> 18248.17
A27: Depreciation offset 21 June to 30 June | D27: =ROUND((C8-D22-D24)/C14*C20,2) -> 11622.66 | E27: =ROUND((C8-E22-E24)/C14*C20,2) -> 16184.71
A30: Cost | D30: =C5 -> 12164247 | E30: =C5 -> 12164247
A31: Accumulated Depreciation | D31: =C6+D21+D26 -> 6429681.1 | E31: =C6+E21+E26 -> 6434243.1
A32: Accumulated Impairment | D32: =D24 -> 2748252 | E32: =E24 -> 1748252
A33: Carrying Value | D33: =D30-D31-D32 -> 2986313.9 | E33: =E30-E31-E32 -> 3981751.8
A34: Revaluation Reserve | D34: =C8-D22-D24-D27 -> 2536065.3 | E34: =C8-E22-E24-E27 -> 3531503.2
A36: RUL | D36: =C14-C20 -> 2182 | E36: =C14-C20 -> 2182
A38: Depreciation 2025 | D38: =ROUND((D33-C15)/D36*365,2) -> 499543.63 | E38: =ROUND((E33-C15)/E36*365,2) -> 666058.23
A39: Depreciation offset 2025 | D39: =ROUND(D34/D36*365,2) -> 424227.23 | E39: =ROUND(E34/E36*365,2) -> 590741.83
A42: Cost | D42: =C5 -> 12164247 | E42: =C5 -> 12164247
A43: Accumulated Depreciation | D43: =D31+D38 -> 6929224.7 | E43: =E31+E38 -> 7100301.4
A44: Accumulated Impairment | D44: =D32 -> 2748252 | E44: =E32 -> 1748252
A45: Carrying Value | D45: =D42-D43-D44 -> 2486770.2 | E45: =E42-E43-E44 -> 3315693.6
A46: Revaluation Reserve | D46: =D34-D39 -> 2111838 | E46: =E34-E39 -> 2940761.4
D48: =D36-365 -> 1817 | E48: =E36-365 -> 1817

Sheet 8
D2: 8.1 | E2: 8.2
B3: Normal without impairment | C3: Impaired to 1200000 | D3: Impairment reversed max | E3: Impairment reversed portion
A5: Cost | B5: 3046098.5 | C5: 3046098.5 | D5: 3046098.5 | E5: 3046098.5
A6: EUL | B6: 3650 | C6: 3650 | D6: 3650 | E6: 3650
A7: Acquisition date | B7: 44941 | C7: 44941 | D7: 44941 | E7: 44941
A8: Residual Value | B8: 1 | C8: 1 | D8: 1 | E8: 1
A9: Impairment date | B9: 45097 | C9: 45097 | D9: 45097 | E9: 45097
B10: 45107 | C10: 45107 | D10: 45107 | E10: 45107
A11: Day is use 20 June 2023 | B11: =B9-B7+1 -> 157 | C11: =C9-C7+1 -> 157 | D11: =D9-D7+1 -> 157 | E11: =E9-E7+1 -> 157
A12: Days in use 20 June to 30 June 2023 | B12: =B10-B7+1-B11 -> 10 | C12: =C10-C7+1-C11 -> 10 | D12: =D10-D7+1-D11 -> 10 | E12: =E10-E7+1-E11 -> 10
A13: Accumulated Depreciation 20 June 2023 | B13: =ROUND((B5-B8)/B6*B11,2) -> 131023.92 | C13: =ROUND((C5-C8)/C6*C11,2) -> 131023.92 | D13: =ROUND((D5-D8)/D6*D11,2) -> 131023.92 | E13: =ROUND((E5-E8)/E6*E11,2) -> 131023.92
A15: Impaired to R1200000 | C15: 1200000 | D15: 1200000 | E15: 1200000
A16: Impairment | C16: =C5-C13-C15 -> 1715074.6 | D16: =D5-D13-D15 -> 1715074.6 | E16: =E5-E13-E15 -> 1715074.6
A17: RUL after impairment | C17: 1460 | D17: 1460 | E17: 1460
A19: Depreciation 21 June to 30 June | B19: =ROUND((B5-B8)/B6*B12,2) -> 8345.47 | C19: =ROUND((C5-C13-C16-C8)/C17*C12,2) -> 8219.17 | D19: =ROUND((D5-D13-D16-D8)/D17*D12,2) -> 8219.17 | E19: =ROUND((E5-E13-E16-E8)/E17*E12,2) -> 8219.17
A21: 2023
A22: Cost | B22: =B5 -> 3046098.5 | C22: =C5 -> 3046098.5 | D22: =D5 -> 3046098.5 | E22: =E5 -> 3046098.5
A23: Accumulated Depreciation | B23: =B13+B19 -> 139369.39 | C23: =C13+C19 -> 139243.09 | D23: =D13+D19 -> 139243.09 | E23: =E13+E19 -> 139243.09
A24: Accumulated Impairment | C24: =C16 -> 1715074.6 | D24: =D16 -> 1715074.6 | E24: =E16 -> 1715074.6
A25: Carrying Value | B25: =B22-B23-B24 -> 2906729.1 | C25: =C22-C23-C24 -> 1191780.8 | D25: =D22-D23-D24 -> 1191780.8 | E25: =E22-E23-E24 -> 1191780.8
A27: RUL | B27: =B6-B11-B12 -> 3483 | C27: =C17-C12 -> 1450 | D27: =D17-D12 -> 1450 | E27: =E17-E12 -> 1450
A29: Impairment reversal on | B29: 45275 | C29: 45275 | D29: 45275 | E29: 45275
B30: 45473 | C30: 45473 | D30: 45473 | E30: 45473
A31: Days in use to impairment reversal | B31: =B29-B10 -> 168 | C31: =C29-C10 -> 168 | D31: =D29-D10 -> 168 | E31: =E29-E10 -> 168
A32: Days in use up to 30 June 2024 | B32: =B30-B29 -> 198 | C32: =C30-C29 -> 198 | D32: =D30-D29 -> 198 | E32: =E30-E29 -> 198
A34: Depreciation 2024 up to impairment reversal | B34: =ROUND((B25-B8)/B27*B31,2) -> 140203.94 | C34: =ROUND((C25-C8)/C27*C31,2) -> 138082.08 | D34: =ROUND((D25-D8)/D27*D31,2) -> 138082.08 | E34: =ROUND((E25-E8)/E27*E31,2) -> 138082.08
A35: Depreciation 2024 up to year end | B35: =ROUND((B25-B8)/B27*B32,2) -> 165240.36 | C35: =ROUND((C25-C8)/C27*C32,2) -> 162739.59 | D35: =ROUND((D25-D34+D36-D8)/D37*D32,2) -> 165240.36 | E35: =ROUND((E25-E34+E36-E8)/E37*E32,2) -> 165180.99
A36: Impairment reversal | B36: =B25-B34 -> 2766525.2 | D36: =B36-(D25-D34) -> 1712826.4 | E36: 800000
A37: RUL at inpairment reversal | B37: =B27-B31 -> 3315 | D37: =B37 -> 3315 | E37: 2222
A39: Cost | B39: =B5 -> 3046098.5 | C39: =C5 -> 3046098.5 | D39: =D5 -> 3046098.5 | E39: =E5 -> 3046098.5
A40: Accumulated Depreciation | B40: =B23+B34+B35 -> 444813.69 | C40: =C23+C34+C35 -> 440064.76 | D40: =D23+D34+D35 -> 442565.53 | E40: =E23+E34+E35 -> 442506.16
A41: Accumulated Impairment | C41: =C24 -> 1715074.6 | D41: =D24-D36 -> 2248.16 | E41: =E24-E36 -> 915074.59
A42: Carrying Value | B42: =B39-B40-B41 -> 2601284.8 | C42: =C39-C40-C41 -> 890959.16 | D42: =D39-D40-D41 -> 2601284.8 | E42: =E39-E40-E41 -> 1688517.8
B44: =B27-B31-B32 -> 3117 | C44: =C27-C31-C32 -> 1084 | D44: =D37-D32 -> 3117 | E44: =E37-E32 -> 2024
A46: Depreciation 2025 | B46: =ROUND(B42/B44*365,2) -> 304609.87 | C46: =ROUND(C42/C44*365,2) -> 300000.09 | D46: =ROUND(D42/D44*365,2) -> 304609.87 | E46: =ROUND(E42/E44*365,2) -> 304500.49
A48: Cost | B48: =B22 -> 3046098.5 | C48: =C22 -> 3046098.5 | D48: =D22 -> 3046098.5 | E48: =E22 -> 3046098.5
A49: Accumulated Depreciation | B49: =B40+B46 -> 749423.56 | C49: =C40+C46 -> 740064.85 | D49: =D40+D46 -> 747175.4 | E49: =E40+E46 -> 747006.65
A50: Accumulated Impairment | C50: =C41 -> 1715074.6 | D50: =D41 -> 2248.16 | E50: =E41 -> 915074.59
A51: Carrying Value | B51: =B48-B49-B50 -> 2296674.9 | C51: =C48-C49-C50 -> 590959.07 | D51: =D48-D49-D50 -> 2296674.9 | E51: =E48-E49-E50 -> 1384017.3
B53: =B44-365 -> 2752 | C53: =C44-365 -> 719 | D53: =D44-365 -> 2752 | E53: =E44-365 -> 1659

Sheet 9
E2: 9.1 | F2: 9.2
B3: Before revaluation | C3: Revaluation 30 June 2022 No impairment | D3: Impaired to R3m on 20 June 2024 | E3: Impaired to R3m on 20 June 2024 Max reversal | F3: Impaired to R3m on 20 June 2024 Partial reversal | H3: 9.1 Asset revalues on 30 June 2022, sunsequently impaired to R3m on 2023/06/20. On 2024/06/20 the impairment was reversed
A5: Cost | B5: 14067804 | C5: 12164247 | D5: 12164247 | E5: 12164247 | F5: 12164247
A6: Accumulated depreciation | B6: 9749246.1 | C6: 6020788.8 | D6: 6020788.8 | E6: 6020788.8 | F6: 6020788.8
A7: Accumulated impairment losses
A8: Revaluation reserve | B8: 3835148.2 | C8: 5660048.6 | D8: 5660048.6 | E8: 5660048.6 | F8: 5660048.6
A9: Carrying Value | B9: =B5-B6 -> 4318557.7 | C9: =C5-C6 -> 6143458.2 | D9: =D5-D6 -> 6143458.2 | E9: =E5-E6 -> 6143458.2 | F9: =F5-F6 -> 6143458.2
A11: EUL | C11: 10957.5 | D11: 10957.5 | E11: 10957.5 | F11: 10957.5
A12: RUL | C12: 5534 | D12: 5534 | E12: 5534 | F12: 5534
A13: RUL after impairment | C13: 2800 | D13: 2800 | E13: 2800 | F13: 2800
A14: Residual Value | C14: 1 | D14: 1 | E14: 1 | F14: 1
A15: Depreciation start date | C15: 44743 | D15: 44743 | E15: 44743 | F15: 44743
A16: Impairment date | C16: 45097 | D16: 45097 | E16: 45097 | F16: 45097
C17: 45107 | D17: 45107 | E17: 45107 | F17: 45107
A18: Day is use 20 June 2023 | C18: =C16-C15+1 -> 355 | D18: =D16-D15+1 -> 355 | E18: =E16-E15+1 -> 355 | F18: =F16-F15+1 -> 355
A19: Days in use 20 June to 30 June 2023 | C19: =C17-C15+1-C18 -> 10 | D19: =D17-D15+1-D18 -> 10 | E19: =E17-E15+1-E18 -> 10 | F19: =F17-F15+1-F18 -> 10
A20: Accumulated Depreciation 20 June 2023 | C20: =ROUND((C9-C14)/C12*C18,2) -> 394096.01 | D20: =ROUND((D9-D14)/D12*D18,2) -> 394096.01 | E20: =ROUND((E9-E14)/E12*E18,2) -> 394096.01 | F20: =ROUND((F9-F14)/F12*F18,2) -> 394096.01
A21: Depreciation offset 20 June 2023 | C21: =ROUND(C8/C12*C18,2) -> 363085.88 | D21: =ROUND(D8/D12*D18,2) -> 363085.88 | E21: =ROUND(E8/E12*E18,2) -> 363085.88 | F21: =ROUND(F8/F12*F18,2) -> 363085.88
A23: Impaired to | D23: 3000000 | E23: 3000000 | F23: 3000000
A24: Impairment | D24: =-D23+(D9-D20) -> 2749362.2 | E24: =-E23+(E9-E20) -> 2749362.2 | F24: =-F23+(F9-F20) -> 2749362.2
A26: Depreciation 21 June to 30 June 2023 | C26: =ROUND((C9-C14)/(C12)*C19,2) -> 11101.3 | D26: =ROUND((D9-D14-D20-D24)/(D13)*D19,2) -> 10714.28 | E26: =ROUND((E9-E14-E20-E24)/(E13)*E19,2) -> 10714.28 | F26: =ROUND((F9-F14-F20-F24)/(F13)*F19,2) -> 10714.28
A27: Depreciation offset 21 June to 30 June 2023 | C27: =ROUND(C8/C12*C19,2) -> 10227.77 | D27: =ROUND((D8-D21-D24)/D13*D19,2) -> 9098.57 | E27: =ROUND((E8-E21-E24)/E13*E19,2) -> 9098.57 | F27: =ROUND((F8-F21-F24)/F13*F19,2) -> 9098.57
A30: Cost | C30: =C5 -> 12164247 | D30: =D5 -> 12164247 | E30: =E5 -> 12164247 | F30: =F5 -> 12164247
A31: Accumulated Depreciation | C31: =C6+C20+C26 -> 6425986.1 | D31: =D6+D20+D26 -> 6425599.1 | E31: =E6+E20+E26 -> 6425599.1 | F31: =F6+F20+F26 -> 6425599.1
A32: Accumulated Impairment | D32: =D24 -> 2749362.2 | E32: =E24 -> 2749362.2 | F32: =F24 -> 2749362.2
A33: Carrying Value | C33: =C30-C31-C32 -> 5738260.9 | D33: =D30-D31-D32 -> 2989285.7 | E33: =E30-E31-E32 -> 2989285.7 | F33: =F30-F31-F32 -> 2989285.7
A34: Revaluation Reserve | C34: =C8-C21-C27 -> 5286735 | D34: =D8-D21-D27-D24 -> 2538502 | E34: =E8-E21-E27-E24 -> 2538502 | F34: =F8-F21-F27-F24 -> 2538502
A36: RUL | C36: =C12-C18-C19 -> 5169 | D36: =D13-D19 -> 2790 | E36: =E13-E19 -> 2790 | F36: =F13-F19 -> 2790
A38: Impairment reversal on | C38: 45275 | D38: 45275 | E38: 45275 | F38: 45275
C39: 45473 | D39: 45473 | E39: 45473 | F39: 45473
A40: Days in use to impairment reversal | C40: =C38-C17 -> 168 | D40: =D38-D17 -> 168 | E40: =E38-E17 -> 168 | F40: =F38-F17 -> 168
A41: Days in use up to 30 June 2024 | C41: =C39-C38 -> 198 | D41: =D39-D38 -> 198 | E41: =E39-E38 -> 198 | F41: =F39-F38 -> 198
A44: Depreciation 2024 up to impairment reversal date | C44: =ROUND((C33-C14)/C36*C40,2) -> 186501.77 | D44: =ROUND((D33-D14)/D36*D40,2) -> 179999.94 | E44: =ROUND((E33-E14)/E36*E40,2) -> 179999.94 | F44: =ROUND((F33-F14)/F36*F40,2) -> 179999.94
A45: Depreciation offset 2024 up to impairment reversal date | C45: =ROUND(C34/C36*C40,2) -> 171826.56 | D45: =ROUND((D34)/D36*D40,2) -> 152856.03 | E45: =ROUND((E34)/E36*E40,2) -> 152856.03 | F45: =ROUND((F34)/F36*F40,2) -> 152856.03
A47: Depreciation 2024 up toyear end | C47: =ROUND((C33-C14)/C36*C41,2) -> 219805.66 | D47: =ROUND((D33-D14)/D36*D41,2) -> 212142.79 | E47: =ROUND((E33-E14-E44+E50)/E51*E41,2) -> 219805.66 | F47: =ROUND((F33-F14-F44+F50)/F51*F41,2) -> 228840.85
A48: Depreciation offset 2024 up to year end | C48: =ROUND(C34/C36*C41,2) -> 202509.87 | D48: =ROUND((D34)/D36*D41,2) -> 180151.75 | E48: =ROUND((E34-E45+E50)/E51*E41,2) -> 203032.92 | F48: =ROUND((F34-F45+F50)/F51*F41,2) -> 205809.42
A50: Impairment reversal | C50: =C33-C44 -> 5551759.1 | E50: =C50-E33+E44 -> 2742473.3 | F50: 1400000
A51: RUL at inpairment reversal | C51: =C36-C40 -> 5001 | E51: 5001 | F51: 3642
A54: Cost | C54: =C30 -> 12164247 | D54: =D30 -> 12164247 | E54: =E30 -> 12164247 | F54: =F30 -> 12164247
A55: Accumulated Depreciation | C55: =C31+C44+C47 -> 6832293.6 | D55: =D31+D44+D47 -> 6817741.9 | E55: =E31+E44+E47 -> 6825404.7 | F55: =F31+F44+F47 -> 6834439.9
A56: Accumulated Impairment | D56: =D32 -> 2749362.2 | E56: =E32-E50 -> 6888.85 | F56: =F32-F50 -> 1349362.2
A57: Carrying Value | C57: =C54-C55-C56 -> 5331953.4 | D57: =D54-D55-D56 -> 2597143 | E57: =E54-E55-E56 -> 5331953.4 | F57: =F54-F55-F56 -> 3980444.9
A58: Revaluation Reserve | C58: =C34-C45-C48 -> 4912398.5 | D58: =D34-D45-D48 -> 2205494.2 | E58: =E34-E45-E48+E50 -> 4925086.4 | F58: =F34-F45-F48+F50 -> 3579836.5
A60: RUL | C60: =C36-C40-C41 -> 4803 | D60: =D36-D40-D41 -> 2424 | E60: =E51-E41 -> 4803 | F60: =F51-F41 -> 3444
A62: Depreciation 2025 | C62: =ROUND((C57-C14)/C60*365,2) -> 405197.3 | D62: =ROUND((D57-D14)/D60*365,2) -> 391071.3 | E62: =ROUND((E57-E14)/E60*365,2) -> 405197.3 | F62: =ROUND((F57-F14)/F60*365,2) -> 421853.09
A63: Depreciation offset 2025 | C63: =ROUND(C58/C60*365,2) -> 373313.65 | D63: =ROUND(D58/D60*365,2) -> 332097.93 | E63: =ROUND(E58/E60*365,2) -> 374277.85 | F63: =ROUND(F58/F60*365,2) -> 379396.15
A66: Cost | C66: =C30 -> 12164247 | D66: =D30 -> 12164247 | E66: =E30 -> 12164247 | F66: =F30 -> 12164247
A67: Accumulated Depreciation | C67: =C55+C62 -> 7237490.9 | D67: =D55+D62 -> 7208813.2 | E67: =E55+E62 -> 7230602 | F67: =F55+F62 -> 7256293
A68: Accumulated Impairment | D68: =D56 -> 2749362.2 | E68: =E56 -> 6888.85 | F68: =F56 -> 1349362.2
A69: Carrying Value | C69: =C66-C67-C68 -> 4926756.1 | D69: =D66-D67-D68 -> 2206071.7 | E69: =E66-E67-E68 -> 4926756.1 | F69: =F66-F67-F68 -> 3558591.8
A70: Revaluation Reserve | C70: =C58-C63 -> 4539084.9 | D70: =D58-D63 -> 1873396.3 | E70: =E58-E63 -> 4550808.5 | F70: =F58-F63 -> 3200440.4
C72: =C60-365 -> 4438 | D72: =D60-365 -> 2059 | E72: =E60-365 -> 4438 | F72: =F60-365 -> 3079

Sheet 10.1
B3: Normal | C3: Disposed
A5: Cost | B5: 3046098.5 | C5: 3046098.5
A6: EUL | B6: 3650 | C6: 3650
A7: Acquisition date | B7: 45306 | C7: 45306
A8: Residual Value | B8: 1 | C8: 1
A9: Disposal date | B9: 45463 | C9: 45463
B10: 45473 | C10: 45473
A11: Day is use 20 June 2024 | B11: =B9-B7+1 -> 158 | C11: =C9-C7+1 -> 158
A12: Days in use 20 June to 30 June | B12: =B10-B7+1-B11 -> 10 | C12: =C10-C7+1-C11 -> 10
A13: Accumulated Depreciation 20 June 2024 | B13: =ROUND((B5-B8)/B6*B11,2) -> 131858.47 | C13: =ROUND((C5-C8)/C6*C11,2) -> 131858.47
A15: Disposal cost | C15: =-C5 -> -3046098.5
A16: Disposal accumulated depreciation | C16: =-C13 -> -131858.47
A18: Depreciation 21 June to 30 June | B18: =ROUND((B5-B8)/B6*B12,2) -> 8345.47
A21: Cost | B21: =B5 -> 3046098.5 | C21: =+C5+C15 -> 0
A22: Accumulated Depreciation | B22: =B13+B18 -> 140203.94 | C22: =C13+C16 -> 0
A23: Accumulated Impairment
A24: Carrying Value | B24: =B21-B22-B23 -> 2905894.6 | C24: =C21-C22-C23 -> 0
A26: RUL | B26: =B6-B11-B12 -> 3482
A28: Depreciation 2025 | B28: =ROUND((B24-B8)/B26*365,2) -> 304609.75
A32: Cost | B32: =B5 -> 3046098.5
A33: Accumulated Depreciation | B33: =B22+B28 -> 444813.69
A34: Accumulated Impairment
A35: Carrying Value | B35: =B32-B33-B34 -> 2601284.8 | C35: =C32-C33-C34 -> 0
B37: =B26-365 -> 3117 | C37: 0

Sheet 10.2
B3: Normal | C3: Impaired | E3: Disposed
A5: Cost | B5: 3046098.5 | C5: 3046098.5 | E5: 3046098.5
A6: EUL | B6: 3650 | C6: 3650 | E6: 3650
A7: Acquisition date | B7: 45306 | C7: 45306 | E7: 45306
A8: Residual Value | B8: 1 | C8: 1 | E8: 1
A9: Impairment date | B9: 45463 | C9: 45463 | E9: 45463
B10: 45473 | C10: 45473 | E10: 45473
A11: Day is use 20 June 2024 | B11: =B9-B7+1 -> 158 | C11: =C9-C7+1 -> 158 | E11: =E9-E7+1 -> 158
A12: Days in use 20 June to 30 June | B12: =B10-B7+1-B11 -> 10 | C12: =C10-C7+1-C11 -> 10 | E12: =E10-E7+1-E11 -> 10
A13: Disposal date | E13: 45468
A14: Days in use 20 June to 25 June | E14: =E13-E9+1 -> 6
A16: Accumulated Depreciation 20 June 2024 | B16: =ROUND((B5-B8)/B6*B11,2) -> 131858.47 | C16: =ROUND((C5-C8)/C6*C11,2) -> 131858.47 | E16: =ROUND((E5-E8)/E6*E11,2) -> 131858.47
A18: Impairment | C18: =C5-C16-1200000 -> 1714240 | E18: =E5-E16-1200000 -> 1714240
A19: RUL after impairment | C19: 730 | E19: 730
A21: Depreciation 21 June to 30 June/ Disposal date | B21: =ROUND((B5-B8)/B6*B12,2) -> 8345.47 | C21: =ROUND((C5-C16-C18-C8)/C19*C12,2) -> 16438.34 | E21: =ROUND((E5-E16-E18-E8)/E19*E14,2) -> 9863.01
A23: Disposal - Cost | E23: =-E5 -> -3046098.5
A24: Disposal - Accumulated Depreciation | E24: =-E16-E21 -> -141721.48
A25: Disposal - Accumulated Impairment | E25: =-E18 -> -1714240
A28: Cost | B28: =B5 -> 3046098.5 | C28: =C5 -> 3046098.5 | E28: =E5+E23 -> 0
A29: Accumulated Depreciation | B29: =B16+B21 -> 140203.94 | C29: =C16+C21 -> 148296.81 | E29: =E16+E21+E24 -> 0
A30: Accumulated Impairment | C30: =C18 -> 1714240 | E30: =E18+E25 -> 0
A31: Carrying Value | B31: =B28-B29-B30 -> 2905894.6 | C31: =C28-C29-C30 -> 1183561.7 | E31: =E28-E29-E30 -> 0
A33: RUL | B33: =B6-B11-B12 -> 3482 | C33: =C19-C12 -> 720
A35: Depreciation 2025 | B35: =ROUND((B31-B8)/B33*365,2) -> 304609.75 | C35: =ROUND((C31-C8)/C33*365,2) -> 599999.5
A39: Cost | B39: =B5 -> 3046098.5 | C39: =C5 -> 3046098.5
A40: Accumulated Depreciation | B40: =B29+B35 -> 444813.69 | C40: =C29+C35 -> 748296.31
A41: Accumulated Impairment | C41: =C30 -> 1714240
A42: Carrying Value | B42: =B39-B40-B41 -> 2601284.8 | C42: =C39-C40-C41 -> 583562.16 | E42: =E39-E40-E41 -> 0
B44: =B33-365 -> 3117 | C44: =C33-365 -> 355

Sheet 11.1
E2: 6.1
B3: Before revaluation | C3: Revaluation 30 June 2023 | D3: Normal | E3: Disposed
A5: Cost | B5: 14067804 | C5: 12164247
A6: Accumulated depreciation | B6: 9749246.1 | C6: 6020788.8
A7: Accumulated impairment losses
A8: Revaluation reserve | B8: 3835148.2 | C8: 5660048.6 | G8: =C8 -> 5660048.6 | H8: =C8 -> 5660048.6
A9: Carrying Value | B9: =B5-B6 -> 4318557.7 | C9: =C5-C6 -> 6143458.2
A11: EUL | C11: 10957.5
A12: RUL | C12: 5534
A13: Residual Value | C13: 1
A14: Depreciation start date | C14: 45108
A15: Disposal date | C15: 45463
C16: 45473
A17: Day is use 20 June 2024 | C17: =C15-C14+1 -> 356
A18: Days in use 20 June to 30 June | C18: =C16-C14+1-C17 -> 10
A19: Accumulated Depreciation 20 June 2024 | D19: =ROUND((C9-C13)/C12*C17,2) -> 395206.14 | E19: =ROUND((C9-C13)/C12*C17,2) -> 395206.14
A20: Depreciation offset 20 June 2024 | D20: =ROUND(C8/C12*C17,2) -> 364108.66 | E20: =ROUND(C8/C12*C17,2) -> 364108.66 | G20: =-D20 -> -364108.66 | H20: =-E20 -> -364108.66
A22: Disposal cost | E22: =-C5 -> -12164247
A23: Disposal Accumulated Depreciation | E23: =-C6-E19 -> -6415995
A24: Disposal Revaluation Reserve | E24: =-C8+E20 -> -5295939.9 | H24: =E24 -> -5295939.9
A26: Depreciation 21 June to 30 June | D26: =ROUND((C9-C13-D19)/C12*C18,2) -> 10387.15
A27: Depreciation offset 21 June to 30 June | D27: =ROUND(C8/C12*C18,2) -> 10227.77 | G27: =-D27 -> -10227.77 | H27: =-E27 -> 0
A30: Cost | D30: =C5 -> 12164247 | E30: =C5+E22 -> 0
A31: Accumulated Depreciation | D31: =C6+D19+D26 -> 6426382.1 | E31: =C6+E19+E23 -> 0
A32: Accumulated Impairment
A33: Carrying Value | D33: =D30-D31-D32 -> 5737864.9 | E33: =E30-E31-E32 -> 0
A34: Revaluation Reserve | D34: =C8-D20-D27 -> 5285712.2 | E34: =C8-E20+E24 -> 0
A36: RUL | D36: =C12-C17-C18 -> 5168
A38: Depreciation 2025 | D38: =ROUND((D33-C13)/D36*365,2) -> 405247.74
A39: Depreciation offset 2025 | D39: =ROUND(D34/D36*365,2) -> 373313.65 | G39: =-D39 -> -373313.65
A42: Cost | D42: =D30 -> 12164247
A43: Accumulated Depreciation | D43: =D31+D38 -> 6831629.9
A44: Accumulated Impairment
A45: Carrying Value | D45: =D42-D43-D44 -> 5332617.1 | E45: =E42-E43-E44 -> 0
A46: Revaluation Reserve | D46: =D34-D39 -> 4912398.5 | E46: =E34-E39 -> 0 | G46: =SUM(G8:G45) -> 4912398.5 | H46: =SUM(H8:H45) -> 0

Sheet 11.2
B3: Before revaluation | C3: Revaluation 30 June 2023 | D3: Before Impairment | E3: Impaired to R3m on 20 June 2024 | F3: Disposed on 25 June 2024
A5: Cost | B5: 14067804 | C5: 12164247
A6: Accumulated depreciation | B6: 9749246.1 | C6: 6020788.8
A7: Accumulated impairment losses
A8: Revaluation reserve | B8: 3835148.2 | C8: 5660048.6
A9: Carrying Value | B9: =B5-B6 -> 4318557.7 | C9: =C5-C6 -> 6143458.2
A11: EUL | C11: 10957.5
A12: RUL | C12: 5534
A13: RUL after impairment | C13: 2192
A14: Residual Value | C14: 1
A15: Depreciation start date | C15: 45108
A16: Impairment date | C16: 45463
C17: 45473
A18: Day is use 20 June 2024 | C18: =C16-C15+1 -> 356
A19: Days in use 20 June to 30 June | C19: =C17-C15+1-C18 -> 10
A20: Disposal date | C20: 45468
A21: Days in use 20 June to 25 June | C21: =C20-C16+1 -> 6
A22: Accumulated Depreciation 20 June 2024 | D22: =ROUND((C9-C14)/C12*C18,2) -> 395206.14 | E22: =ROUND((C9-C14)/C12*C18,2) -> 395206.14 | F22: =ROUND((C9-C14)/C12*C18,2) -> 395206.14
A23: Depreciation offset 20 June 2024 | D23: =ROUND(C8/C12*C18,2) -> 364108.66 | E23: =ROUND(C8/C12*C18,2) -> 364108.66 | F23: =ROUND(C8/C12*C18,2) -> 364108.66
A25: Impairment | E25: =-3000000+(C9-E22) -> 2748252 | F25: =-3000000+(C9-F22) -> 2748252
A27: Depreciation 21 June to 30 June/ disposal date | D27: =ROUND((C9-C14-D22)/C12*C19,2) -> 10387.15 | E27: =ROUND((C9-C14-E22-E25)/C13*C19,2) -> 13686.13 | F27: =ROUND((C9-C14-F22-E25)/C13*C21,2) -> 8211.68
A28: Depreciation offset 21 June to 30 June/ disposal date | D28: =ROUND(C8/C12*C19,2) -> 10227.77 | E28: =ROUND((C8-E23-E25)/C13*C19,2) -> 11622.66 | F28: =ROUND((C8-F23-E25)/C13*C21,2) -> 6973.6
A30: Disposal - Cost | F30: =-C5 -> -12164247
A31: Disposal - Accumulated Depreciation | F31: =-C6-F22-F27 -> -6424206.7
A32: Disposal - Accumulated Impairment | F32: =-F25 -> -2748252
A33: Disposal - Revaluation Reserve | F33: =-C8+F23+F28+F25 -> -2540714.3
A36: Cost | D36: =C5 -> 12164247 | E36: =C5 -> 12164247 | F36: =C5+F30 -> 0
A37: Accumulated Depreciation | D37: =C6+D22+D27 -> 6426382.1 | E37: =C6+E22+E27 -> 6429681.1 | F37: =C6+F22+F27+F31 -> 0
A38: Accumulated Impairment | E38: =E25 -> 2748252 | F38: =F25+F32 -> 0
A39: Carrying Value | D39: =D36-D37-D38 -> 5737864.9 | E39: =E36-E37-E38 -> 2986313.9 | F39: =F36-F37-F38 -> 0
A40: Revaluation Reserve | D40: =C8-D23-D28 -> 5285712.2 | E40: =C8-E23-E25-E28 -> 2536065.3 | F40: =C8-F23-F25-F28+F33 -> 0
A42: RUL | D42: =C12-C18-C19 -> 5168 | E42: =C13-C19 -> 2182 | F42: 0
A44: Depreciation 2025 | D44: =ROUND((D39-C14)/D42*365,2) -> 405247.74 | E44: =ROUND((E39-C14)/E42*365,2) -> 499543.63
A45: Depreciation offset 2025 | D45: =ROUND(D40/D42*365,2) -> 373313.65 | E45: =ROUND(E40/E42*365,2) -> 424227.23
A48: Cost | D48: =D36 -> 12164247 | E48: =E36 -> 12164247
A49: Accumulated Depreciation | D49: =D37+D44 -> 6831629.9 | E49: =E37+E44 -> 6929224.7
A50: Accumulated Impairment | E50: =E38 -> 2748252
A51: Carrying Value | D51: =D48-D49-D50 -> 5332617.1 | E51: =E48-E49-E50 -> 2486770.2 | F51: =F48-F49-F50 -> 0
A52: Revaluation Reserve | D52: =D40-D45 -> 4912398.5 | E52: =E40-E45 -> 2111838 | F52: =F40-F45 -> 0
